Workbook

Sheet Sales Report
B1: Sales Report | D1: ='Report date'!A1 -> Date: 12/01/2026
A2: Store | B2: (All)
B4: Year
B5: 2019 | D5: 2020 | F5: 2021 | H5: 2022 | J5: 2023 | L5: 2024 | N5: 2025 | P5: 2026
A6: Month | B6: Revenue | C6: YoY % | D6: Revenue | E6: YoY % | F6: Revenue | G6: YoY % | H6: Revenue | I6: YoY % | J6: Revenue | K6: YoY % | L6: Revenue | M6: YoY % | N6: Revenue | O6: YoY % | P6: Revenue | Q6: YoY %
A7: 1 | B7: 76719682 | E7: #NULL! | F7: 42168182 | H7: 24034545 | I7: -0.43003127 | J7: 178571682 | K7: 6.4297925 | L7: 319354676 | M7: 0.78838365 | N7: 1598650371 | O7: 4.0058774 | P7: 2245706114 | Q7: 0.40475125
A8: 2 | D8: 150208045 | F8: 42925454 | G8: -0.71422666 | H8: 54000000 | I8: 0.25799485 | J8: 301744182 | K8: 4.5878552 | L8: 388104091 | M8: 0.2862024 | N8: 1210626251 | O8: 2.1193339 | Q8: #NULL!
A9: 3 | B9: 25389818 | D9: 0 | E9: -1 | F9: 42807273 | G9: #DIV/0! | I9: #NULL! | J9: 533360046 | L9: 735902871 | M9: 0.37974878 | N9: 2311571297 | O9: 2.1411364 | Q9: #NULL!
A10: 4 | B10: 36936000 | E10: #NULL! | G10: #NULL! | H10: 21393519 | J10: 190421182 | K10: 7.9008817 | L10: 942539999 | M10: 3.9497645 | N10: 610269166 | O10: -0.35252704 | Q10: #NULL!
A11: 5 | B11: 22621818 | E11: #NULL! | F11: 37387272 | H11: 0 | I11: -1 | J11: 619795091 | K11: #DIV/0! | L11: 925603781 | M11: 0.49340289 | N11: 4766652824 | O11: 4.1497767 | Q11: #NULL!
A12: 6 | B12: 343331091 | E12: #NULL! | F12: 17048182 | I12: #NULL! | J12: 55300910 | L12: 4149523395 | M12: 74.035355 | N12: 3712396249 | O12: -0.10534394 | Q12: #NULL!
A13: 7 | E13: #NULL! | G13: #NULL! | H13: 100218056 | J13: 237744445 | K13: 1.3722716 | L13: 824277917 | M13: 2.4670754 | N13: 4258808381 | O13: 4.1667142 | Q13: #NULL!
A14: 8 | B14: 10369091 | E14: #NULL! | G14: #NULL! | H14: 112107037 | J14: 339686389 | K14: 2.0300184 | L14: 2559864824 | M14: 6.5359653 | N14: 2162270418 | O14: -0.15531852 | Q14: #NULL!
A15: 9 | B15: 5890909 | E15: #NULL! | G15: #NULL! | H15: 47254629 | J15: 213412222 | K15: 3.5162183 | L15: 1488737404 | M15: 5.975877 | N15: 2854688742 | O15: 0.91752336 | Q15: #NULL!
A16: 10 | B16: 54352728 | D16: 90669191 | E16: 0.66816265 | G16: #NULL! | H16: 7921296 | J16: 592350912 | K16: 73.779545 | L16: 1152640624 | M16: 0.94587465 | N16: 3639300556 | O16: 2.1573593 | Q16: #NULL!
A17: 11 | E17: #NULL! | G17: #NULL! | H17: 49240509 | J17: 506547954 | K17: 9.2872201 | L17: 4973764234 | M17: 8.8189405 | N17: 2962751583 | O17: -0.40432408 | Q17: #NULL!
A18: 12 | B18: 84050910 | E18: #NULL! | F18: 0 | H18: 1087499630 | I18: #DIV/0! | J18: 614834535 | K18: -0.43463472 | L18: 1539075325 | M18: 1.503235 | N18: 3172471909 | O18: 1.0612844 | Q18: #NULL!
A19: Grand Total | B19: 659662047 | D19: 240877236 | E19: -0.63484751 | F19: 182336363 | G19: -0.24303199 | H19: 1503669221 | I19: 7.2466777 | J19: 4383769550 | K19: 1.9153816 | L19: 19999389141 | M19: 3.5621443 | N19: 33260457747 | O19: 0.66307368 | P19: 2245706114 | Q19: -0.9324812
A21: Store | B21: RHN
B23: Year
B24: 2019 | D24: 2020 | F24: 2021 | H24: 2022 | J24: 2023 | L24: 2024 | N24: 2025 | P24: 2026
A25: Month | B25: Revenue | C25: YoY % | D25: Revenue | E25: YoY % | F25: Revenue | G25: YoY % | H25: Revenue | I25: YoY % | J25: Revenue | K25: YoY % | L25: Revenue | M25: YoY % | N25: Revenue | O25: YoY % | P25: Revenue | Q25: YoY %
A26: 1 | B26: 23752727 | E26: #NULL! | F26: 33007273 | I26: #NULL! | K26: #NULL! | M26: #NULL! | N26: 872008241 | P26: 1974673521 | Q26: 1.2645125
A27: 2 | D27: 150208045 | F27: 42925454 | G27: -0.71422666 | H27: 39420000 | I27: -0.081663761 | J27: 31694545 | K27: -0.19597806 | M27: #NULL! | O27: #NULL! | Q27: #NULL!
A28: 3 | B28: 25389818 | E28: #NULL! | G28: #NULL! | I28: #NULL! | J28: 12872727 | L28: 97898193 | M28: 6.6050858 | N28: 381069444 | O28: 2.8925074 | Q28: #NULL!
A29: 4 | B29: 36936000 | E29: #NULL! | G29: #NULL! | H29: 21393519 | J29: 45096364 | K29: 1.1079451 | L29: 270427685 | M29: 4.9966627 | N29: 303890231 | O29: 0.12373935 | Q29: #NULL!
A30: 5 | E30: #NULL! | G30: #NULL! | I30: #NULL! | J30: 19135455 | L30: 796691853 | M30: 40.63433 | N30: 4143968889 | O30: 4.2014701 | Q30: #NULL!
A31: 6 | B31: 305163546 | E31: #NULL! | F31: 17048182 | I31: #NULL! | J31: 5498182 | L31: 3329951589 | M31: 604.64594 | N31: 1671288379 | O31: -0.4981043 | Q31: #NULL!
A32: 7 | E32: #NULL! | G32: #NULL! | H32: 93580556 | K32: #NULL! | L32: 31668473 | N32: 2986425000 | O32: 93.302779 | Q32: #NULL!
A33: 8 | B33: 8130000 | E33: #NULL! | G33: #NULL! | H33: 23845833 | J33: 7280556 | K33: -0.69468225 | L33: 2545599083 | M33: 348.6435 | N33: 1382540001 | O33: -0.45689012 | Q33: #NULL!
A34: 9 | B34: 5890909 | E34: #NULL! | G34: #NULL! | I34: #NULL! | K34: #NULL! | L34: 1412596478 | N34: 2762150593 | O34: 0.95537129 | Q34: #NULL!
A35: 10 | B35: 16966364 | D35: 53124545 | E35: 2.1311685 | G35: #NULL! | H35: 7921296 | J35: 32600926 | K35: 3.1156051 | L35: 878561920 | M35: 25.948987 | N35: 3632080556 | O35: 3.1341202 | Q35: #NULL!
A36: 11 | E36: #NULL! | G36: #NULL! | H36: 41319213 | J36: 170666666 | K36: 3.1304433 | L36: 3484943029 | M36: 19.419588 | N36: 2867827833 | O36: -0.17708043 | Q36: #NULL!
A37: 12 | B37: 54615455 | E37: #NULL! | G37: #NULL! | H37: 296296296 | K37: #NULL! | L37: 1186570232 | N37: 1841254028 | O37: 0.55174467 | Q37: #NULL!
A38: Grand Total | B38: 476844819 | D38: 203332590 | E38: -0.5735875 | F38: 92980909 | G38: -0.54271517 | H38: 523776713 | I38: 4.633164 | J38: 324845421 | K38: -0.37980171 | L38: 14034908535 | M38: 42.204883 | N38: 22844503195 | O38: 0.62769163 | P38: 1974673521 | Q38: -0.91356023
A40: Store | B40: RWR
B42: Year
B43: 2019 | D43: 2020 | F43: 2021 | H43: 2022 | J43: 2023 | L43: 2024 | N43: 2025 | P43: 2026
A44: Month | B44: Revenue | C44: YoY % | D44: Revenue | E44: YoY % | F44: Revenue | G44: YoY % | H44: Revenue | I44: YoY % | J44: Revenue | K44: YoY % | L44: Revenue | M44: YoY % | N44: Revenue | O44: YoY % | P44: Revenue | Q44: YoY %
A45: 1 | B45: 52966955 | E45: #NULL! | F45: 9160909 | H45: 24034545 | I45: 1.6235983 | J45: 170794409 | K45: 6.1062052 | L45: 43450926 | M45: -0.74559515 | N45: 699045186 | O45: 15.088154 | P45: 185056667 | Q45: -0.73527224
A46: 2 | E46: #NULL! | G46: #NULL! | H46: 14580000 | J46: 253316001 | K46: 16.374211 | L46: 252951036 | M46: -0.0014407499 | N46: 1183360325 | O46: 3.6782189 | Q46: #NULL!
A47: 3 | D47: 0 | F47: 42807273 | G47: #DIV/0! | I47: #NULL! | J47: 407474410 | L47: 27500001 | M47: -0.9325111 | N47: 1878796713 | O47: 67.319878 | Q47: #NULL!
A48: 4 | E48: #NULL! | G48: #NULL! | I48: #NULL! | J48: 145324818 | L48: 103323981 | M48: -0.28901352 | N48: 289953935 | O48: 1.8062598 | Q48: #NULL!
A49: 5 | B49: 22621818 | E49: #NULL! | F49: 37387272 | I49: #NULL! | J49: 589663272 | L49: 84249260 | M49: -0.8571231 | N49: 580108009 | O49: 5.8856155 | Q49: #NULL!
A50: 6 | B50: 38167545 | E50: #NULL! | G50: #NULL! | I50: #NULL! | J50: 27240000 | L50: 790075695 | M50: 28.004247 | N50: 2034707870 | O50: 1.5753328 | Q50: #NULL!
A51: 7 | E51: #NULL! | G51: #NULL! | H51: 6637500 | J51: 5189815 | K51: -0.21810697 | L51: 596261111 | M51: 113.89063 | N51: 1121479677 | O51: 0.8808533 | Q51: #NULL!
A52: 8 | B52: 2239091 | E52: #NULL! | G52: #NULL! | H52: 88261204 | K52: #NULL! | M52: #NULL! | N52: 592060046 | Q52: #NULL!
A53: 9 | E53: #NULL! | G53: #NULL! | H53: 47254629 | K53: #NULL! | L53: 61415926 | N53: 53105000 | O53: -0.135322 | Q53: #NULL!
A54: 10 | B54: 37386364 | E54: #NULL! | G54: #NULL! | I54: #NULL! | J54: 17576852 | L54: 262185185 | M54: 13.916504 | O54: #NULL! | Q54: #NULL!
A55: 11 | E55: #NULL! | G55: #NULL! | H55: 7921296 | J55: 111058890 | K55: 13.020293 | L55: 1343332454 | M55: 11.095677 | N55: 67456157 | O55: -0.94978447 | Q55: #NULL!
A56: 12 | B56: 29435455 | E56: #NULL! | G56: #NULL! | H56: 774541297 | J56: 621780000 | K56: -0.19722809 | L56: 352505093 | M56: -0.43307103 | N56: 1309413251 | O56: 2.7145939 | Q56: #NULL!
A57: Grand Total | B57: 182817228 | D57: 0 | E57: -1 | F57: 89355454 | G57: #DIV/0! | H57: 963230471 | I57: 9.7797614 | J57: 2349418467 | K57: 1.4391031 | L57: 3917250668 | M57: 0.66732778 | N57: 9809486169 | O57: 1.5041763 | P57: 185056667 | Q57: -0.98113493
A59: Store | B59: RWT
B61: Year
B62: 2022 | D62: 2023 | F62: 2024 | H62: 2025 | J62: 2026
A63: Month | B63: Revenue | C63: YoY % | D63: Revenue | E63: YoY % | F63: Revenue | G63: YoY % | H63: Revenue | I63: YoY % | J63: Revenue | K63: YoY %
A64: 1 | D64: 7777273 | G64: #NULL! | H64: 12176852 | J64: 85975926 | K64: 6.0606037
A65: 2 | D65: 16733636 | G65: #NULL! | H65: 18625926 | K65: #NULL!
A66: 3 | D66: 37201818 | F66: 13662964 | G66: -0.63273397 | H66: 44501853 | I66: 2.2571156 | K66: #NULL!
A67: 4 | E67: #NULL! | F67: 56441667 | H67: 16425000 | I67: -0.70899159 | K67: #NULL!
A68: 5 | D68: 10996364 | F68: 31715741 | G68: 1.8842025 | H68: 42575926 | I68: 0.34242255 | K68: #NULL!
A69: 6 | D69: 22562728 | F69: 12836111 | G69: -0.43109224 | H69: 6400000 | I69: -0.50140662 | K69: #NULL!
A70: 7 | D70: 15600000 | F70: 61579629 | G70: 2.9474121 | H70: 79868519 | I70: 0.29699578 | K70: #NULL!
A71: 8 | D71: 6009259 | F71: 7065741 | G71: 0.17580903 | H71: 4248148 | I71: -0.39876823 | K71: #NULL!
A72: 9 | E72: #NULL! | F72: 14725000 | H72: 33352593 | I72: 1.2650318 | K72: #NULL!
A73: 10 | D73: 5189815 | F73: 11893519 | G73: 1.2917038 | H73: 7220000 | I73: -0.3929467 | K73: #NULL!
A74: 11 | E74: #NULL! | F74: 61233427 | H74: 27467593 | I74: -0.55142813 | K74: #NULL!
A75: 12 | B75: 16662037 | D75: 19769444 | E75: 0.18649622 | G75: #NULL! | H75: 21804630 | K75: #NULL!
A76: Grand Total | B76: 16662037 | D76: 141840337 | E76: 7.5127849 | F76: 271153799 | G76: 0.91168327 | H76: 314667040 | I76: 0.16047439 | J76: 85975926 | K76: -0.72677175
A78: Store | B78: RWD
B80: Year
B81: 2023 | D81: 2024 | F81: 2025
A82: Month | B82: Revenue | C82: YoY % | D82: Revenue | E82: YoY % | F82: Revenue | G82: YoY %
A83: 1 | D83: 275903750 | F83: 15420092 | G83: -0.94411061
A84: 2 | D84: 135153055 | F84: 8640000 | G84: -0.93607248
A85: 3 | D85: 21230556 | F85: 7203287 | G85: -0.66071134
A86: 4 | D86: 50309629 | G86: #NULL!
A87: 5 | D87: 19767037 | G87: #NULL!
A88: 6 | D88: 16660000 | G88: #NULL!
A89: 7 | B89: 216954630 | D89: 21248704 | E89: -0.90205923 | F89: 71035185 | G89: 2.3430361
A90: 8 | B90: 326396574 | D90: 7200000 | E90: -0.97794094 | F90: 16755556 | G90: 1.3271606
A91: 9 | B91: 213412222 | E91: #NULL! | F91: 6080556
A92: 10 | B92: 536983319 | E92: #NULL! | G92: #NULL!
A93: 11 | B93: 224822398 | D93: 84255324 | E93: -0.62523608 | G93: #NULL!
A94: 12 | B94: -81844815 | E94: #NULL! | G94: #NULL!
A95: Grand Total | B95: 1436724328 | D95: 631728055 | E95: -0.56029974 | F95: 125134676 | G95: -0.80191686
A97: Store | B97: RWR
B99: Year
B100: 2019 | D100: 2020 | F100: 2021 | H100: 2022 | J100: 2023 | L100: 2024 | N100: 2025 | P100: 2026
A101: Month | B101: Revenue | C101: YoY % | D101: Revenue | E101: YoY % | F101: Revenue | G101: YoY % | H101: Revenue | I101: YoY % | J101: Revenue | K101: YoY % | L101: Revenue | M101: YoY % | N101: Revenue | O101: YoY % | P101: Revenue | Q101: YoY %
A102: 1 | B102: 52966955 | E102: #NULL! | F102: 9160909 | H102: 24034545 | I102: 1.6235983 | J102: 170794409 | K102: 6.1062052 | L102: 43450926 | M102: -0.74559515 | N102: 699045186 | O102: 15.088154 | P102: 185056667 | Q102: -0.73527224
A103: 2 | E103: #NULL! | G103: #NULL! | H103: 14580000 | J103: 253316001 | K103: 16.374211 | L103: 252951036 | M103: -0.0014407499 | N103: 1183360325 | O103: 3.6782189 | Q103: #NULL!
A104: 3 | D104: 0 | F104: 42807273 | G104: #DIV/0! | I104: #NULL! | J104: 407474410 | L104: 27500001 | M104: -0.9325111 | N104: 1878796713 | O104: 67.319878 | Q104: #NULL!
A105: 4 | E105: #NULL! | G105: #NULL! | I105: #NULL! | J105: 145324818 | L105: 103323981 | M105: -0.28901352 | N105: 289953935 | O105: 1.8062598 | Q105: #NULL!
A106: 5 | B106: 22621818 | E106: #NULL! | F106: 37387272 | I106: #NULL! | J106: 589663272 | L106: 84249260 | M106: -0.8571231 | N106: 580108009 | O106: 5.8856155 | Q106: #NULL!
A107: 6 | B107: 38167545 | E107: #NULL! | G107: #NULL! | I107: #NULL! | J107: 27240000 | L107: 790075695 | M107: 28.004247 | N107: 2034707870 | O107: 1.5753328 | Q107: #NULL!
A108: 7 | E108: #NULL! | G108: #NULL! | H108: 6637500 | J108: 5189815 | K108: -0.21810697 | L108: 596261111 | M108: 113.89063 | N108: 1121479677 | O108: 0.8808533 | Q108: #NULL!
A109: 8 | B109: 2239091 | E109: #NULL! | G109: #NULL! | H109: 88261204 | K109: #NULL! | M109: #NULL! | N109: 592060046 | Q109: #NULL!
A110: 9 | E110: #NULL! | G110: #NULL! | H110: 47254629 | K110: #NULL! | L110: 61415926 | N110: 53105000 | O110: -0.135322 | Q110: #NULL!
A111: 10 | B111: 37386364 | E111: #NULL! | G111: #NULL! | I111: #NULL! | J111: 17576852 | L111: 262185185 | M111: 13.916504 | O111: #NULL! | Q111: #NULL!
...

Sheet Sales by Vendor
A1: Phân loại | B1: Lấy BC | D1: Sales Report | E1: ='Report date'!A1 -> Date: 12/01/2026
A3: Revenue | B3: Year
A4: Vendor | B4: 2019 | C4: 2020 | D4: 2021 | E4: 2022 | F4: 2023 | G4: 2024 | H4: 2025 | I4: 2026
A5: ARTUR SCHOLL | E5: 1070837593 | F5: 271510818 | G5: 1351948909 | H5: 2575321252
A6: BURATO | H6: 1229180556 | I6: 319764816
A7: GEODE | E7: 287584027 | F7: 114901010 | G7: 320891716 | H7: 167089817
A8: GIORGIO VISCONTI | F8: 189498409 | G8: 1820174444 | H8: 1181890370
A9: MARIAE LUISA | F9: 379105984 | G9: 425868972 | H9: 613241438 | I9: 106256482
A10: NAK ARMSTRONG | C10: 84920909 | F10: 825924260 | G10: 758590619 | H10: 3871146843 | I10: 911472222
A11: NANIS | F11: 1371603144 | G11: 1546597223 | H11: 6898910295 | I11: 674486667
A12: ROSA MARIA | B12: 598174183 | C12: 118411681 | D12: 102141818 | E12: 121213056 | F12: 884461038 | G12: 950910380 | H12: 672616666 | I12: 9262963
A13: SPINELLI KILCOLLIN | B13: 61487864 | D13: 37387272 | E13: 24034545 | F13: 316418523 | G13: 217347223 | H13: 163379860
A14: Ted Muehling | D14: 42807273 | F14: 30346364 | H14: 0
A15: VHERNIER | G15: 12031448498 | H15: 15887680650 | I15: 224462964
A16: Grand Total | B16: 659662047 | C16: 203332590 | D16: 182336363 | E16: 1503669221 | F16: 4383769550 | G16: 19423777984 | H16: 33260457747 | I16: 2245706114

Sheet Inventory by Vendor
A1: Inventory Report | B1: ='Report date'!A1 -> Date: 12/01/2026
B3: Store
B4: HQ | D4: INTRAN | F4: LOA | H4: RHN | J4: RWD | L4: RWR | N4: RWT | P4: Total Qty | Q4: Total Landed Cost
A5: Vendor | B5: Qty | C5: Landed Cost | D5: Qty | E5: Landed Cost | F5: Qty | G5: Landed Cost | H5: Qty | I5: Landed Cost | J5: Qty | K5: Landed Cost | L5: Qty | M5: Landed Cost | N5: Qty | O5: Landed Cost
A6: ARTUR SCHOLL | F6: 1 | G6: 105556804 | H6: 13 | I6: 1113789248 | L6: 10 | M6: 857160748 | P6: 24 | Q6: 2076506800
A7: BURATO | B7: 1 | C7: 15036518 | H7: 43 | I7: 9.3779722e+08 | L7: 12 | M7: 2.3419019e+08 | P7: 56 | Q7: 1.1870239e+09
A8: CONFUORTO GIOIELLY ITALY | J8: 2 | K8: 2088000 | N8: 5 | O8: 7027500 | P8: 7 | Q8: 9115500
A9: GEODE | B9: 4 | C9: 11423101 | H9: 7 | I9: 8845472 | J9: 7 | K9: 6558500 | L9: 9 | M9: 26630567 | N9: 14 | O9: 13065325 | P9: 41 | Q9: 66522965
A10: GIORGIO VISCONTI | H10: 11 | I10: 672328445 | L10: 12 | M10: 845578220 | P10: 23 | Q10: 1517906665
A11: GOLDEN CORALS | H11: 11 | I11: 95009500 | L11: 16 | M11: 127705500 | N11: 2 | O11: 1121000 | P11: 29 | Q11: 223836000
A12: MARIAE LUISA | D12: 1 | E12: 7962040 | H12: 33 | I12: 167762816 | J12: 13 | K12: 74912542 | L12: 28 | M12: 182424744 | N12: 25 | O12: 118547635 | P12: 100 | Q12: 551609777
A13: NAK ARMSTRONG | F13: 2 | G13: 381183460 | H13: 4 | I13: 528508930 | L13: 10 | M13: 1588954694 | P13: 16 | Q13: 2498647084
A14: NANIS | B14: 6 | C14: 170505015 | D14: 2 | E14: 57940405 | H14: 51 | I14: 2.0478181e+09 | L14: 40 | M14: 1.864519e+09 | P14: 99 | Q14: 4140782603
A15: ROSA MARIA | F15: 3 | G15: 21406128 | H15: 43 | I15: 418706977 | J15: 1 | K15: 1491338 | L15: 21 | M15: 222704062 | P15: 68 | Q15: 664308505
A16: SPINELLI KILCOLLIN | H16: 4 | I16: 360977556 | L16: 4 | M16: 409496635 | P16: 8 | Q16: 770474191
A17: Ted Muehling | B17: 1 | C17: 24300000 | H17: 17 | I17: 923265250 | L17: 9 | M17: 416718023 | P17: 27 | Q17: 1364283273
A18: VHERNIER | B18: 5 | C18: 1265279223 | F18: 1 | G18: 134963747 | H18: 23 | I18: 4764867923 | L18: 57 | M18: 6741741112 | P18: 86 | Q18: 12906852005
A19: Grand Total | B19: 17 | C19: 1486543857 | D19: 3 | E19: 65902445 | F19: 7 | G19: 643110139 | H19: 260 | I19: 1.2039677e+10 | J19: 23 | K19: 85050380 | L19: 228 | M19: 1.3517824e+10 | N19: 46 | O19: 139761460 | P19: 584 | Q19: 2.7977869e+10

Sheet Inventory by Season
A1: Inventory Report | C1: ='Report date'!A1 -> Date: 12/01/2026
B3: Store
B4: HQ | D4: INTRAN | F4: LOA | H4: RHN | J4: RWD | L4: RWR | N4: RWT | P4: Total Qty | Q4: Total Landed Cost
A5: Season | B5: Qty | C5: Landed Cost | D5: Qty | E5: Landed Cost | F5: Qty | G5: Landed Cost | H5: Qty | I5: Landed Cost | J5: Qty | K5: Landed Cost | L5: Qty | M5: Landed Cost | N5: Qty | O5: Landed Cost
A6: FW11 | L6: 1 | M6: 3698446 | P6: 1 | Q6: 3698446
A7: FW16 | H7: 1 | I7: 9475200 | L7: 1 | M7: 1945800 | P7: 2 | Q7: 11421000
A8: FW17 | L8: 1 | M8: 34545000 | P8: 1 | Q8: 34545000
A9: FW22 | B9: 3 | C9: 5287101 | H9: 13 | I9: 52689478 | L9: 14 | M9: 435997761 | N9: 2 | O9: 1121000 | P9: 32 | Q9: 495095340
A10: FW23 | H10: 3 | I10: 339737181 | J10: 2 | K10: 2871000 | L10: 5 | M10: 226185523 | P10: 10 | Q10: 568793704
A11: FW24 | F11: 1 | G11: 105556804 | H11: 14 | I11: 534773770 | L11: 23 | M11: 1647543377 | N11: 5 | O11: 4657825 | P11: 43 | Q11: 2292531776
A12: FW25 | B12: 1 | C12: 15036518 | F12: 1 | G12: 134963747 | H12: 19 | I12: 835066495 | J12: 2 | K12: 8176822 | L12: 32 | M12: 2551954292 | N12: 1 | O12: 3129646 | P12: 56 | Q12: 3548327520
A13: SS19 | H13: 3 | I13: 33346950 | P13: 3 | Q13: 33346950
A14: SS20 | H14: 2 | I14: 18084675 | P14: 2 | Q14: 18084675
A15: SS22 | B15: 1 | C15: 6136000 | J15: 1 | K15: 1062000 | L15: 16 | M15: 116525000 | N15: 3 | O15: 4867500 | P15: 21 | Q15: 128590500
A16: SS23 | B16: 1 | C16: 22925672 | F16: 4 | G16: 69598715 | H16: 33 | I16: 699336724 | J16: 3 | K16: 18951875 | L16: 11 | M16: 168356867 | N16: 15 | O16: 74223214 | P16: 67 | Q16: 1053393067
A17: SS24 | B17: 4 | C17: 112249828 | D17: 1 | E17: 7962040 | F17: 1 | G17: 332990873 | H17: 59 | I17: 1456257454 | J17: 10 | K17: 50301183 | L17: 36 | M17: 1064224700 | N17: 11 | O17: 43354775 | P17: 122 | Q17: 3067340853
A18: SS25 | B18: 5 | C18: 1265279223 | H18: 19 | I18: 1249033750 | J18: 5 | K18: 3687500 | L18: 25 | M18: 2345990527 | N18: 9 | O18: 8407500 | P18: 63 | Q18: 4872398500
A19: SS26 | B19: 2 | C19: 59629515 | D19: 2 | E19: 57940405 | H19: 94 | I19: 6.8118758e+09 | L19: 63 | M19: 4.9208563e+09 | P19: 161 | Q19: 1.1850302e+10
A20: Grand Total | B20: 17 | C20: 1486543857 | D20: 3 | E20: 65902445 | F20: 7 | G20: 643110139 | H20: 260 | I20: 1.2039677e+10 | J20: 23 | K20: 85050380 | L20: 228 | M20: 1.3517824e+10 | N20: 46 | O20: 139761460 | P20: 584 | Q20: 2.7977869e+10

Sheet Associate RHN
B1: Sales Report | D1: ='Report date'!A1 -> Date: 12/01/2026
A2: Status Associate | B2: Active
A3: Store | B3: RHN
B5: Year
B6: 2019 | D6: 2020 | F6: 2021 | H6: 2022 | J6: 2023 | L6: 2024 | N6: 2025 | P6: 2026
A7: Associate | B7: Revenue | C7: YoY % | D7: Revenue | E7: YoY % | F7: Revenue | G7: YoY % | H7: Revenue | I7: YoY % | J7: Revenue | K7: YoY % | L7: Revenue | M7: YoY % | N7: Revenue | O7: YoY % | P7: Revenue | Q7: YoY %
A8: CHINH_NGUYEN | B8: 79292182 | E8: #NULL! | F8: 6152727 | H8: 62726390 | I8: 9.1948924 | J8: 8850000 | K8: -0.85891106 | L8: 1087668750 | M8: 121.90042 | N8: 3149309065 | O8: 1.8954671 | Q8: #NULL!
A9: HUE_BUI | B9: 5890909 | E9: #NULL! | F9: 42925454 | H9: 3550926 | I9: -0.91727691 | J9: 45554461 | K9: 11.828896 | L9: 1192671620 | M9: 25.181226 | N9: 1596530555 | O9: 0.33861704 | P9: 156953704 | Q9: -0.90169076
A10: HUYEN_DANG | D10: 26913500 | F10: 33007273 | G10: 0.22642068 | H10: 47778333 | I10: 0.44750925 | J10: 97190320 | K10: 1.0341924 | L10: 1728666203 | M10: 16.786403 | N10: 2151144259 | O10: 0.24439539 | P10: 243808334 | Q10: -0.8866611
A11: MINH_TAM | E11: #NULL! | G11: #NULL! | I11: #NULL! | K11: #NULL! | M11: #NULL! | N11: 3961867592 | Q11: #NULL!
A12: NGHIA_NGUYEN | B12: 108083455 | E12: #NULL! | G12: #NULL! | I12: #NULL! | K12: #NULL! | M12: #NULL! | O12: #NULL! | Q12: #NULL!
A13: NGHIA_NGUYEN_HNSM | E13: #NULL! | G13: #NULL! | I13: #NULL! | K13: #NULL! | M13: #NULL! | N13: 8233624317 | P13: 1451108705 | Q13: -0.82375821
A14: NGOC_DUONG | E14: #NULL! | G14: #NULL! | I14: #NULL! | K14: #NULL! | M14: #NULL! | N14: 288234260 | P14: 9262963 | Q14: -0.96786307
A15: NGOC_LE | E15: #NULL! | G15: #NULL! | I15: #NULL! | K15: #NULL! | M15: #NULL! | N15: 773097360 | P15: 61900926 | Q15: -0.91993127
A16: PHAN_ANH | E16: #NULL! | G16: #NULL! | I16: #NULL! | K16: #NULL! | M16: #NULL! | N16: 1152174166 | Q16: #NULL!
A17: SON_NGUYENVAN | E17: #NULL! | G17: #NULL! | I17: #NULL! | K17: #NULL! | M17: #NULL! | N17: 486628704 | Q17: #NULL!
A18: THUY_DANG | E18: #NULL! | G18: #NULL! | I18: #NULL! | K18: #NULL! | M18: #NULL! | N18: 516357454 | P18: 51638889 | Q18: -0.89999391
A19: TRUNG_HIEU | E19: #NULL! | G19: #NULL! | I19: #NULL! | K19: #NULL! | M19: #NULL! | N19: 502477130 | Q19: #NULL!
A22: Status Associate | B22: Active
A23: Store | B23: RHN
A24: Year | B24: 2025
A26: Revenue | B26: Month
A27: Associate | B27: 1 | C27: 3 | D27: 4 | E27: 5 | F27: 6 | G27: 7 | H27: 8 | I27: 9 | J27: 10 | K27: 11 | L27: 12 | M27: Grand Total
A28: CHINH_NGUYEN | B28: 862330463 | C28: 58348148 | F28: 239017361 | G28: 972594167 | I28: 385009667 | J28: 243120370 | K28: 388888889 | M28: 3149309065
A29: HUE_BUI | C29: 322721296 | F29: 22398889 | I29: 1102137222 | J29: 149273148 | M29: 1596530555
A30: HUYEN_DANG | E30: 62288333 | F30: 119330741 | G30: 217133333 | H30: 799977963 | I30: 439237963 | J30: 453403704 | K30: 59772222 | M30: 2151144259
A31: MINH_TAM | B31: 5663889 | E31: 3780425000 | G31: 132206481 | I31: 43572222 | M31: 3961867592
A32: NGHIA_NGUYEN_HNSM | D32: 136882685 | E32: 78111991 | F32: 692219166 | G32: 1122196297 | H32: 145755556 | I32: 347314815 | J32: 2767705556 | K32: 1234795334 | L32: 1708642917 | M32: 8233624317
A33: NGOC_DUONG | I33: 288234260 | M33: 288234260
A34: NGOC_LE | D34: 151469583 | F34: 438776852 | G34: 26206481 | I34: 156644444 | M34: 773097360
A35: PHAN_ANH | H35: 179340741 | K35: 972833425 | M35: 1152174166
A36: SON_NGUYENVAN | G36: 17625000 | H36: 257465741 | K36: 211537963 | M36: 486628704
A37: THUY_DANG | E37: 223143565 | F37: 142025000 | J37: 18577778 | L37: 132611111 | M37: 516357454
A38: TRUNG_HIEU | B38: 4013889 | G38: 498463241 | M38: 502477130

Sheet Sales TY
A1: Year | B1: Month | C1: Week | D1: Seaseon1 | E1: Cate | F1: Season | G1: Landed cost | H1: Base cost | I1: Date | J1: Item | K1: Store&Bill | L1: Vendor | M1: Store | N1: Dept | O1: Bill | P1: Qty Sold | Q1: Payment form | R1: Payment | S1: Revenue | T1: Discount % | U1: Discount (Ex VAT) | V1: Discount | W1: Cashier | X1: Description | Y1: Full Name | Z1: Item Name | AA1: Hour | AB1: Attribute | AC1: Full Price | AD1: Size | AE1: Full Price(Ex VAT) | AF1: Associate | AG1: Phone Number | AH1: Lợi nhuận gộp | AI1: Phân loại | AJ1: Status Associate
A2: 2019 | B2: 1 | C2: 2 | D2: SS17 | E2: JEWELRY | F2: SS17 | G2: 13991896 | H2: 10827625 | I2: 43477 | J2: 109007 | K2: RWR294 | L2: SPINELLI KILCOLLIN | M2: RWR | N2: WACC | O2: 294 | P2: 1 | Q2: Cash | R2: 26511650 | S2: 24101500 | T2: 5 | U2: 1268500 | V2: 1395350 | W2: Ha_Nguyen | X2: SPK Sirius SG Single band of sterling silver with 18k yellow gold accents and micro-pavé black diamonds | Y2: Mrs. Pham Thuy Nga | Z2: SG12-R-G4S2YGAPCG | AA2: 16 | AB2: GOLD | AC2: 27907000 | AD2: 6 | AE2: 25370000 | AF2: TAM_LE | AG2: 0908545384 | AH2: 10109604 | AI2: =VLOOKUP(Sales[[#This Row],[Store]],'Store lay bao cao'!A:B,2,0) -> Lấy BC | AJ2: =VLOOKUP(Sales[[#This Row],[Associate]],'Associate Status'!B:C,2,0) -> Retired
A3: 2019 | B3: 1 | C3: 3 | D3: SS18 | E3: RING | F3: SS18 | G3: 11433892 | H3: 11249280 | I3: 43483 | J3: 117933 | K3: RHN715 | L3: ROSA MARIA | M3: RHN | N3: WACC | O3: 715 | P3: 1 | Q3: Cash | R3: 26128000 | S3: 23752727 | T3: 20 | U3: 5938182 | V3: 6532000 | W3: Huyen_Dang | X3: RM SILVER RING-TOP SILVER TREATED FRAME SET WITH COGNAC DIAMONDS -MIDDLE BROWN RUTILATED QUARTZ | Y3: Ms. Dinh My Hanh | Z3: JULIA (1) S-ST DIA (CO-BRN RUT. | AA3: 15 | AB3: COGNAC/BROWN | AC3: 32660000 | AD3: 11 | AE3: 29690909 | AF3: SYSADMIN | AG3: 0904043388 | AH3: 12318835 | AI3: =VLOOKUP(Sales[[#This Row],[Store]],'Store lay bao cao'!A:B,2,0) -> Lấy BC | AJ3: =VLOOKUP(Sales[[#This Row],[Associate]],'Associate Status'!B:C,2,0) -> Retired
A4: 2019 | B4: 1 | C4: 4 | D4: SS17 | E4: JEWELRY | F4: SS17 | G4: 26510963 | H4: 20515500 | I4: 43486 | J4: 109005 | K4: GIF14 | L4: SPINELLI KILCOLLIN | M4: GIF | N4: WACC | O4: 14 | P4: 1 | Q4: None | R4: 0 | S4: 0 | T4: 100 | U4: 48068182 | V4: 52875000 | W4: Oanh_Do | X4: SPK Libra SG 3 linked rings in silver with yellow gold connectors and micro-pave grey diamonds | Y4: Cong ty Globallink | Z4: SG12-R-G3MXMMXGC | AA4: 15 | AB4: GOLD | AC4: 52875000 | AD4: 7 | AE4: 48068182 | AF4: SYSADMIN | AH4: -26510963 | AI4: =VLOOKUP(Sales[[#This Row],[Store]],'Store lay bao cao'!A:B,2,0) -> Không lấy BC | AJ4: =VLOOKUP(Sales[[#This Row],[Associate]],'Associate Status'!B:C,2,0) -> Retired
A5: 2019 | B5: 1 | C5: 5 | D5: SS18 | E5: NECKLACE | F5: SS18 | G5: 11116284 | H5: 10936800 | I5: 43493 | J5: 117928 | K5: RWR441 | L5: ROSA MARIA | M5: RWR | N5: WACC | O5: 441 | P5: 1 | Q5: Split | R5: 31752000 | S5: 28865455 | T5: 0 | U5: 0 | V5: 0 | W5: Ha_Nguyen | X5: RM SILVER TREATED CHAIN+SILVER MEDAL -TOP SILVER TREATED FRAME SET WITH COGNAC DIAMONDS-MIDDLE BROWN RUTILATED QUARTZ | Y5: Mrs. Phan Lan Phuong | Z5: PE 102G S-ST DIA (CO (2R)-BRN R | AA5: 17 | AB5: COGNAC/BROWN | AC5: 31752000 | AD5: U | AE5: 28865455 | AF5: CHI_NGUYEN | AG5: 0977317777 | AH5: 17749171 | AI5: =VLOOKUP(Sales[[#This Row],[Store]],'Store lay bao cao'!A:B,2,0) -> Lấy BC | AJ5: =VLOOKUP(Sales[[#This Row],[Associate]],'Associate Status'!B:C,2,0) -> Retired
A6: 2019 | B6: 3 | C6: 11 | D6: SS18 | E6: RING | F6: SS18 | G6: 7365600 | H6: 7365600 | I6: 43539 | J6: 117944 | K6: RHN1352 | L6: ROSA MARIA | M6: RHN | N6: WACC | O6: 1352 | P6: 1 | Q6: Split | R6: 20314800 | S6: 18468000 | T6: 5 | U6: 972000 | V6: 1069200 | W6: Phuong_Bui | X6: RM SILVER TWISTED BELL FLOWER RING-TOP SILVER-MIDDLE silver | Y6: Mrs. Ngo Phuong Ly | Z6: SAXO (4) S-S-S | AA6: 10 | AB6: SILVER | AC6: 21384000 | AD6: 11 | AE6: 19440000 | AF6: CHINH_NGUYEN | AG6: 0943448888 | AH6: 11102400 | AI6: =VLOOKUP(Sales[[#This Row],[Store]],'Store lay bao cao'!A:B,2,0) -> Lấy BC | AJ6: =VLOOKUP(Sales[[#This Row],[Associate]],'Associate Status'!B:C,2,0) -> Active
A7: 2019 | B7: 3 | C7: 12 | D7: FW16 | E7: JEWELRY | F7: FW16 | G7: 2284200 | H7: 2284200 | I7: 43548 | J7: 90588 | K7: RHN1449 | L7: ROSA MARIA | M7: RHN | N7: WACC | O7: 1449 | P7: 1 | Q7: Cash | R7: 7614000 | S7: 6921818 | T7: 0 | U7: 0 | V7: 0 | W7: Phuong_Bui | X7: RM SILVER SNAKE RING(Mat) | Y7: Mrs. Pham Hai Van | Z7: PENN | AA7: 14 | AC7: 7614000 | AD7: 12 | AE7: 6921818 | AF7: CHINH_NGUYEN | AG7: 0944659999 | AH7: 4637618 | AI7: =VLOOKUP(Sales[[#This Row],[Store]],'Store lay bao cao'!A:B,2,0) -> Lấy BC | AJ7: =VLOOKUP(Sales[[#This Row],[Associate]],'Associate Status'!B:C,2,0) -> Active
A8: 2019 | B8: 4 | C8: 15 | D8: SS18 | E8: RING | F8: SS18 | G8: 7486477 | H8: 7365600 | I8: 43563 | J8: 117940 | K8: RHN1576 | L8: ROSA MARIA | M8: RHN | N8: WACC | O8: 1576 | P8: 1 | Q8: Split | R8: 20314800 | S8: 18468000 | T8: 5 | U8: 972000 | V8: 1069200 | W8: Phuong_Bui | X8: RM SILVER RING INTO 2:(1)TOP SILVER FLOWER-MIDDLE SILVER TOP SILVER TREATED PETALS + SILVER TREATED PISTILS SET WITH RUBIS -(1)SILVER TREATED HEAD SET WITH (1)COGNAC DIAMOND | Y8: Mrs. Ngo Phuong Ly | Z8: BOANKA S S ST S ST DIX (RU)-ST | AA8: 19 | AB8: SILVER/RUBIS | AC8: 21384000 | AD8: 12 | AE8: 19440000 | AF8: CHINH_NGUYEN | AG8: 0943448888 | AH8: 10981523 | AI8: =VLOOKUP(Sales[[#This Row],[Store]],'Store lay bao cao'!A:B,2,0) -> Lấy BC | AJ8: =VLOOKUP(Sales[[#This Row],[Associate]],'Associate Status'!B:C,2,0) -> Active
A9: 2019 | B9: 4 | C9: 15 | D9: SS18 | E9: RING | F9: SS18 | G9: 7365600 | H9: 7365600 | I9: 43563 | J9: 117952 | K9: RHN1576 | L9: ROSA MARIA | M9: RHN | N9: WACC | O9: 1576 | P9: 1 | Q9: Split | R9: 20314800 | S9: 18468000 | T9: 5 | U9: 972000 | V9: 1069200 | W9: Phuong_Bui | X9: RM SILVER RING INTO 2:(1)TOP SILVER FLOWER-MIDDLE SILVER TOP SILVER TREATED PETALS + SILVER TREATED PISTILS SET WITH RUBIS -(1)SILVER TREATED HEAD SET WITH (1)COGNAC DIAMOND | Y9: Mrs. Ngo Phuong Ly | Z9: BOANKA S S ST S ST DIX (RU)-ST | AA9: 19 | AB9: SILVER/RUBIS | AC9: 21384000 | AD9: 11 | AE9: 19440000 | AF9: CHINH_NGUYEN | AG9: 0943448888 | AH9: 11102400 | AI9: =VLOOKUP(Sales[[#This Row],[Store]],'Store lay bao cao'!A:B,2,0) -> Lấy BC | AJ9: =VLOOKUP(Sales[[#This Row],[Associate]],'Associate Status'!B:C,2,0) -> Active
A10: 2019 | B10: 5 | C10: 19 | D10: SS18 | E10: EARRINGS | F10: SS18 | G10: 4553280 | H10: 4553280 | I10: 43595 | J10: 117920 | K10: RWR1037 | L10: ROSA MARIA | M10: RWR | N10: WACC | O10: 1037 | P10: 1 | Q10: Check | R10: 13220000 | S10: 12018182 | T10: 0 | U10: 0 | V10: 0 | W10: Hang_Nguyen | X10: RM SILVER DROP EARRINGS -TOP SILVER FRAME SET WITH ICY GREY DIAMONDS-MIDDLE SMOKY QUARTZ | Y10: Ms. To Mai Lien | Z10: BO 113 (V)DIA (ICY GRIS-S.QTZ) | AA10: 15 | AB10: SILVER/ICY G | AC10: 13220000 | AD10: U | AE10: 12018182 | AF10: HUONG_NGUYENKIM | AG10: 0936462242 | AH10: 7464902 | AI10: =VLOOKUP(Sales[[#This Row],[Store]],'Store lay bao cao'!A:B,2,0) -> Lấy BC | AJ10: =VLOOKUP(Sales[[#This Row],[Associate]],'Associate Status'!B:C,2,0) -> Active
A11: 2019 | B11: 5 | C11: 19 | D11: SS18 | E11: BRACELET | F11: SS18 | G11: 4083533 | H11: 4017600 | I11: 43595 | J11: 117931 | K11: RWR1037 | L11: ROSA MARIA | M11: RWR | N11: WACC | O11: 1037 | P11: 1 | Q11: Check | R11: 11664000 | S11: 10603636 | T11: 0 | U11: 0 | V11: 0 | W11: Hang_Nguyen | X11: RM SILVER ROUND SNAKE BRACELET-TOP MEDAL FRAMED WITH ICY GREY DIAMONDS-MIDDLE SMOKY QUARTZ (Transparent)-QUEUE END SET WITH (1)RUBIS | Y11: Ms. To Mai Lien | Z11: BR/TOVE(1)(V)DIA (ICY GRIS-S.QT | AA11: 15 | AB11: SILVER/ICY G | AC11: 11664000 | AD11: S | AE11: 10603636 | AF11: HUONG_NGUYENKIM | AG11: 0936462242 | AH11: 6520103 | AI11: =VLOOKUP(Sales[[#This Row],[Store]],'Store lay bao cao'!A:B,2,0) -> Lấy BC | AJ11: =VLOOKUP(Sales[[#This Row],[Associate]],'Associate Status'!B:C,2,0) -> Active
A12: 2019 | B12: 6 | C12: 25 | D12: FW12 | E12: JEWELRY | F12: FW12 | G12: 17531100 | H12: 17531100 | I12: 43633 | J12: 42533 | K12: RHN2159 | L12: ROSA MARIA | M12: RHN | N12: WACC | O12: 2159 | P12: 1 | Q12: Cash | R12: 55515150 | S12: 50468318 | T12: 5 | U12: 2656227 | V12: 2921850 | W12: Ngoc_Nguyen | X12: RM Silver ring-top (1 1/2mm)silver treated frame set with rubis-middle topaz | Y12: Ms. To Thi Hanh | Z12: JUNYA(V) S-ST C1 1/2 DIA(RU-TOP | AA12: 16 | AB12: SILVER | AC12: 58437000 | AD12: 9 | AE12: 53124545 | AF12: LINH_PHAN | AG12: 0916671961 | AH12: 32937218 | AI12: =VLOOKUP(Sales[[#This Row],[Store]],'Store lay bao cao'!A:B,2,0) -> Lấy BC | AJ12: =VLOOKUP(Sales[[#This Row],[Associate]],'Associate Status'!B:C,2,0) -> Retired
A13: 2019 | B13: 6 | C13: 25 | D13: SS13 | E13: JEWELRY | F13: SS13 | G13: 21867638 | H13: 21867638 | I13: 43633 | J13: 52838 | K13: RHN2159 | L13: ROSA MARIA | M13: RHN | N13: WACC | O13: 2159 | P13: 1 | Q13: Cash | R13: 69240750 | S13: 62946136 | T13: 5 | U13: 3312955 | V13: 3644250 | W13: Ngoc_Nguyen | X13: RM Silver ring-top silver treated frame set with icy grey diamonds-middle topaz(transparent) | Y13: Ms. To Thi Hanh | Z13: SHINE(V)S-STDIA (ICY GRIS-TOPAZ | AA13: 16 | AB13: Silver/grey/topa | AC13: 72885000 | AD13: 12 | AE13: 66259091 | AF13: LINH_PHAN | AG13: 0916671961 | AH13: 41078498 | AI13: =VLOOKUP(Sales[[#This Row],[Store]],'Store lay bao cao'!A:B,2,0) -> Lấy BC | AJ13: =VLOOKUP(Sales[[#This Row],[Associate]],'Associate Status'!B:C,2,0) -> Retired
A14: 2019 | B14: 6 | C14: 25 | D14: SS18 | E14: EARRINGS | F14: SS18 | G14: 8370000 | H14: 8370000 | I14: 43633 | J14: 117919 | K14: RHN2159 | L14: ROSA MARIA | M14: RHN | N14: WACC | O14: 2159 | P14: 1 | Q14: Cash | R14: 23085000 | S14: 20986364 | T14: 5 | U14: 1104545 | V14: 1215000 | W14: Ngoc_Nguyen | X14: RM SILVER DROP EARRINGS -TOP SILVER FRAME SET WITH ICY GREY DIAMONDS-MIDDLE SMOKY QUARTZ | Y14: Ms. To Thi Hanh | Z14: BO 114 (V)DIA (ICY GRIS(2R)-S.Q | AA14: 16 | AB14: SILVER/ICY G | AC14: 24300000 | AD14: U | AE14: 22090909 | AF14: LINH_PHAN | AG14: 0916671961 | AH14: 12616364 | AI14: =VLOOKUP(Sales[[#This Row],[Store]],'Store lay bao cao'!A:B,2,0) -> Lấy BC | AJ14: =VLOOKUP(Sales[[#This Row],[Associate]],'Associate Status'!B:C,2,0) -> Retired
A15: 2019 | B15: 6 | C15: 25 | D15: SS18 | E15: RING | F15: SS18 | G15: 24998400 | H15: 24998400 | I15: 43635 | J15: 117945 | K15: RHN2176 | L15: ROSA MARIA | M15: RHN | N15: WACC | O15: 2176 | P15: 1 | Q15: Credit Card | R15: 68947200 | S15: 62679273 | T15: 5 | U15: 3298909 | V15: 3628800 | W15: Phuong_Bui | X15: RM SILVER RING-TOP SILVER TREATED FRAME SET WITH COGNAC DIAMONDS-MIDDLE BROWN RUTILATED((Transparent)) | Y15: Ms. To Thi Hanh | Z15: ROBERTA(V)SP S-ST DIA(CO-BRN RU | AA15: 17 | AB15: COGNAC/BROWN | AC15: 72576000 | AD15: 12 | AE15: 65978182 | AF15: LINH_PHAN | AG15: 0916671961 | AH15: 37680873 | AI15: =VLOOKUP(Sales[[#This Row],[Store]],'Store lay bao cao'!A:B,2,0) -> Lấy BC | AJ15: =VLOOKUP(Sales[[#This Row],[Associate]],'Associate Status'!B:C,2,0) -> Retired
A16: 2019 | B16: 6 | C16: 26 | D16: SS13 | E16: JEWELRY | F16: SS13 | G16: 15578273 | H16: 15578273 | I16: 43640 | J16: 52828 | K16: RHN2220 | L16: ROSA MARIA | M16: RHN | N16: WACC | O16: 2220 | P16: 1 | Q16: Credit Card | R16: 46730700 | S16: 42482455 | T16: 10 | U16: 4720273 | V16: 5192300 | W16: Ngoc_Nguyen | X16: RM Silver ring-top silver treated frame set with icy grey diamonds-middle topaz | Y16: Ms. Hoang Phuong Loan | Z16: BIKRAM (TH) S-ST DIA(ICY GRIS-T | AA16: 14 | AB16: Silver/grey/topa | AC16: 51923000 | AD16: 11 | AE16: 47202727 | AF16: NGHIA_NGUYEN | AG16: 0965562828 | AH16: 26904182 | AI16: =VLOOKUP(Sales[[#This Row],[Store]],'Store lay bao cao'!A:B,2,0) -> Lấy BC | AJ16: =VLOOKUP(Sales[[#This Row],[Associate]],'Associate Status'!B:C,2,0) -> Active
A17: 2019 | B17: 6 | C17: 26 | D17: SS12 | E17: JEWELRY | F17: SS12 | G17: 9504000 | H17: 9504000 | I17: 43640 | J17: 37094 | K17: RHN2220 | L17: ROSA MARIA | M17: RHN | N17: WACC | O17: 2220 | P17: 1 | Q17: Credit Card | R17: 31990500 | S17: 29082273 | T17: 10 | U17: 3231364 | V17: 3554500 | W17: Ngoc_Nguyen | X17: RM Silver treated ring-top framed with black diamonds-middle smoky quartz | Y17: Ms. Hoang Phuong Loan | Z17: BEGUM R(TH)ST DIA(BLK.DIAM-QUAR | AA17: 14 | AB17: SILVER | AC17: 35545000 | AD17: 11 | AE17: 32313636 | AF17: NGHIA_NGUYEN | AG17: 0965562828 | AH17: 19578273 | AI17: =VLOOKUP(Sales[[#This Row],[Store]],'Store lay bao cao'!A:B,2,0) -> Lấy BC | AJ17: =VLOOKUP(Sales[[#This Row],[Associate]],'Associate Status'!B:C,2,0) -> Active
A18: 2019 | B18: 6 | C18: 26 | D18: SS13 | E18: JEWELRY | F18: SS13 | G18: 13391509 | H18: 13391509 | I18: 43640 | J18: 52823 | K18: RHN2220 | L18: ROSA MARIA | M18: RHN | N18: WACC | O18: 2220 | P18: 1 | Q18: Credit Card | R18: 40170600 | S18: 36518727 | T18: 10 | U18: 4057636 | V18: 4463400 | W18: Ngoc_Nguyen | X18: RM Silver ring-top (4mm) silver | Y18: Ms. Hoang Phuong Loan | Z18: CARRIE R (TH) S-ST C4 DIA(BLK D | AA18: 14 | AB18: SILVER/BLACK | AC18: 44634000 | AD18: 10 | AE18: 40576364 | AF18: NGHIA_NGUYEN | AG18: 0965562828 | AH18: 23127218 | AI18: =VLOOKUP(Sales[[#This Row],[Store]],'Store lay bao cao'!A:B,2,0) -> Lấy BC | AJ18: =VLOOKUP(Sales[[#This Row],[Associate]],'Associate Status'!B:C,2,0) -> Active
A19: 2019 | B19: 6 | C19: 26 | D19: SS18 | E19: RING | F19: SS18 | G19: 15222240 | H19: 15222240 | I19: 43643 | J19: 117951 | K19: RWR1298 | L19: ROSA MARIA | M19: RWR | N19: WACC | O19: 1298 | P19: 1 | Q19: Account | R19: 44194000 | S19: 40176364 | T19: 0 | U19: 0 | V19: 0 | W19: Ha_Nguyen | X19: RM SILVER RING INTO 2:(1) SILVER TREATED FRAME SET WITH ICY GREY DIAMONDS-MIDDLE SILVER (CONCAVE)-(1)(4mm) SILVER TREATED FRAME SET WITH ICY GREY DIAMONDS-MIDDLE BEER QUARTZ | Y19: Mrs. Phan Lan Phuong | Z19: BELCAR S-ST-S DIX (ICY GRIS)-S | AA19: 19 | AB19: SILVER/ICY G | AC19: 44194000 | AD19: 10 | AE19: 40176364 | AF19: DIEM_NGUYEN | AG19: 0977317777 | AH19: 24954124 | AI19: =VLOOKUP(Sales[[#This Row],[Store]],'Store lay bao cao'!A:B,2,0) -> Lấy BC | AJ19: =VLOOKUP(Sales[[#This Row],[Associate]],'Associate Status'!B:C,2,0) -> Retired
A20: 2019 | B20: 6 | C20: 26 | D20: SS18 | E20: RING | F20: SS18 | G20: -15222240 | H20: -15222240 | I20: 43644 | J20: 117951 | K20: RWR1313 | L20: ROSA MARIA | M20: RWR | N20: WACC | O20: 1313 | P20: -1 | Q20: None | R20: -44194000 | S20: -40176364 | T20: 0 | U20: 0 | V20: 0 | W20: Hang_Nguyen | X20: RM SILVER RING INTO 2:(1) SILVER TREATED FRAME SET WITH ICY GREY DIAMONDS-MIDDLE SILVER (CONCAVE)-(1)(4mm) SILVER TREATED FRAME SET WITH ICY GREY DIAMONDS-MIDDLE BEER QUARTZ | Y20: Mrs. Phan Lan Phuong | Z20: BELCAR S-ST-S DIX (ICY GRIS)-S | AA20: 16 | AB20: SILVER/ICY G | AC20: -44194000 | AD20: 10 | AE20: -40176364 | AF20: DIEM_NGUYEN | AG20: 0977317777 | AH20: -24954124 | AI20: =VLOOKUP(Sales[[#This Row],[Store]],'Store lay bao cao'!A:B,2,0) -> Lấy BC | AJ20: =VLOOKUP(Sales[[#This Row],[Associate]],'Associate Status'!B:C,2,0) -> Retired
A21: 2019 | B21: 6 | C21: 26 | D21: SS18 | E21: RING | F21: SS18 | G21: 15222240 | H21: 15222240 | I21: 43644 | J21: 117951 | K21: RWR1313 | L21: ROSA MARIA | M21: RWR | N21: WACC | O21: 1313 | P21: 1 | Q21: None | R21: 41984300 | S21: 38167545 | T21: 5 | U21: 2008818 | V21: 2209700 | W21: Hang_Nguyen | X21: RM SILVER RING INTO 2:(1) SILVER TREATED FRAME SET WITH ICY GREY DIAMONDS-MIDDLE SILVER (CONCAVE)-(1)(4mm) SILVER TREATED FRAME SET WITH ICY GREY DIAMONDS-MIDDLE BEER QUARTZ | Y21: Mrs. Phan Lan Phuong | Z21: BELCAR S-ST-S DIX (ICY GRIS)-S | AA21: 16 | AB21: SILVER/ICY G | AC21: 44194000 | AD21: 10 | AE21: 40176364 | AF21: DIEM_NGUYEN | AG21: 0977317777 | AH21: 22945305 | AI21: =VLOOKUP(Sales[[#This Row],[Store]],'Store lay bao cao'!A:B,2,0) -> Lấy BC | AJ21: =VLOOKUP(Sales[[#This Row],[Associate]],'Associate Status'!B:C,2,0) -> Retired
A22: 2019 | B22: 6 | C22: 26 | D22: SS18 | E22: RING | F22: SS18 | G22: -15222240 | H22: -15222240 | I22: 43644 | J22: 117951 | K22: RWR1311 | L22: ROSA MARIA | M22: RWR | N22: WACC | O22: 1311 | P22: -1 | Q22: None | R22: -44194000 | S22: -40176364 | T22: 0 | U22: 0 | V22: 0 | W22: Hang_Nguyen | X22: RM SILVER RING INTO 2:(1) SILVER TREATED FRAME SET WITH ICY GREY DIAMONDS-MIDDLE SILVER (CONCAVE)-(1)(4mm) SILVER TREATED FRAME SET WITH ICY GREY DIAMONDS-MIDDLE BEER QUARTZ | Y22: Mrs. Phan Lan Phuong | Z22: BELCAR S-ST-S DIX (ICY GRIS)-S | AA22: 16 | AB22: SILVER/ICY G | AC22: -44194000 | AD22: 10 | AE22: -40176364 | AF22: DIEM_NGUYEN | AG22: 0977317777 | AH22: -24954124 | AI22: =VLOOKUP(Sales[[#This Row],[Store]],'Store lay bao cao'!A:B,2,0) -> Lấy BC | AJ22: =VLOOKUP(Sales[[#This Row],[Associate]],'Associate Status'!B:C,2,0) -> Retired
A23: 2019 | B23: 6 | C23: 26 | D23: SS18 | E23: RING | F23: SS18 | G23: 15222240 | H23: 15222240 | I23: 43644 | J23: 117951 | K23: RWR1311 | L23: ROSA MARIA | M23: RWR | N23: WACC | O23: 1311 | P23: 1 | Q23: None | R23: 41984300 | S23: 38167545 | T23: 5 | U23: 2008818 | V23: 2209700 | W23: Hang_Nguyen | X23: RM SILVER RING INTO 2:(1) SILVER TREATED FRAME SET WITH ICY GREY DIAMONDS-MIDDLE SILVER (CONCAVE)-(1)(4mm) SILVER TREATED FRAME SET WITH ICY GREY DIAMONDS-MIDDLE BEER QUARTZ | Y23: Mrs. Phan Lan Phuong | Z23: BELCAR S-ST-S DIX (ICY GRIS)-S | AA23: 16 | AB23: SILVER/ICY G | AC23: 44194000 | AD23: 10 | AE23: 40176364 | AF23: HANG_NGUYEN | AG23: 0977317777 | AH23: 22945305 | AI23: =VLOOKUP(Sales[[#This Row],[Store]],'Store lay bao cao'!A:B,2,0) -> Lấy BC | AJ23: =VLOOKUP(Sales[[#This Row],[Associate]],'Associate Status'!B:C,2,0) -> Retired
A24: 2019 | B24: 6 | C24: 26 | D24: SS18 | E24: RING | F24: SS18 | G24: 15222240 | H24: 15222240 | I24: 43644 | J24: 117951 | K24: RWR1312 | L24: ROSA MARIA | M24: RWR | N24: WACC | O24: 1312 | P24: 1 | Q24: Account | R24: 44194000 | S24: 40176364 | T24: 0 | U24: 0 | V24: 0 | W24: Hang_Nguyen | X24: RM SILVER RING INTO 2:(1) SILVER TREATED FRAME SET WITH ICY GREY DIAMONDS-MIDDLE SILVER (CONCAVE)-(1)(4mm) SILVER TREATED FRAME SET WITH ICY GREY DIAMONDS-MIDDLE BEER QUARTZ | Y24: Mrs. Phan Lan Phuong | Z24: BELCAR S-ST-S DIX (ICY GRIS)-S | AA24: 16 | AB24: SILVER/ICY G | AC24: 44194000 | AD24: 10 | AE24: 40176364 | AF24: DIEM_NGUYEN | AG24: 0977317777 | AH24: 24954124 | AI24: =VLOOKUP(Sales[[#This Row],[Store]],'Store lay bao cao'!A:B,2,0) -> Lấy BC | AJ24: =VLOOKUP(Sales[[#This Row],[Associate]],'Associate Status'!B:C,2,0) -> Retired
A25: 2019 | B25: 6 | C25: 26 | D25: SS18 | E25: RING | F25: SS18 | G25: -15222240 | H25: -15222240 | I25: 43644 | J25: 117951 | K25: RWR1312 | L25: ROSA MARIA | M25: RWR | N25: WACC | O25: 1312 | P25: -1 | Q25: Account | R25: -41984300 | S25: -38167545 | T25: 5 | U25: -2008818 | V25: -2209700 | W25: Hang_Nguyen | X25: RM SILVER RING INTO 2:(1) SILVER TREATED FRAME SET WITH ICY GREY DIAMONDS-MIDDLE SILVER (CONCAVE)-(1)(4mm) SILVER TREATED FRAME SET WITH ICY GREY DIAMONDS-MIDDLE BEER QUARTZ | Y25: Mrs. Phan Lan Phuong | Z25: BELCAR S-ST-S DIX (ICY GRIS)-S | AA25: 16 | AB25: SILVER/ICY G | AC25: -44194000 | AD25: 10 | AE25: -40176364 | AF25: HANG_NGUYEN | AG25: 0977317777 | AH25: -22945305 | AI25: =VLOOKUP(Sales[[#This Row],[Store]],'Store lay bao cao'!A:B,2,0) -> Lấy BC | AJ25: =VLOOKUP(Sales[[#This Row],[Associate]],'Associate Status'!B:C,2,0) -> Retired
A26: 2019 | B26: 8 | C26: 32 | D26: SS18 | E26: EARRINGS | F26: SS18 | G26: 3080160 | H26: 3080160 | I26: 43688 | J26: 117921 | K26: RHN2944 | L26: ROSA MARIA | M26: RHN | N26: WACC | O26: 2944 | P26: 1 | Q26: Credit Card | R26: 8943000 | S26: 8130000 | T26: 0 | U26: 0 | V26: 0 | W26: Ngoc_Nguyen | X26: RM SILVER STUDS FLOWERS EARRINGS SET PAVING WITH COGNAC DIAMONDS | Y26: Mrs. Nguyen Duc Hanh | Z26: BO NILOUFAR (3)(D) DIA (CO) | AA26: 18 | AB26: SILVER/COGNA | AC26: 8943000 | AD26: U | AE26: 8130000 | AF26: KIEUDIEM_NGUYEN | AG26: 0834336699 | AH26: 5049840 | AI26: =VLOOKUP(Sales[[#This Row],[Store]],'Store lay bao cao'!A:B,2,0) -> Lấy BC | AJ26: =VLOOKUP(Sales[[#This Row],[Associate]],'Associate Status'!B:C,2,0) -> #N/A
A27: 2019 | B27: 8 | C27: 35 | D27: SS18 | E27: EARRINGS | F27: SS18 | G27: 848160 | H27: 848160 | I27: 43707 | J27: 117922 | K27: RWR1628 | L27: ROSA MARIA | M27: RWR | N27: WACC | O27: 1628 | P27: 1 | Q27: Credit Card | R27: 2463000 | S27: 2239091 | T27: 0 | U27: 0 | V27: 0 | W27: Hang_Nguyen | X27: RM SILVER STUDS FLOWERS EARRINGS | Y27: Nguyen Thi Le Ha | Z27: BO NILOUFAR (3)(D) | AA27: 13 | AB27: SILVER | AC27: 2463000 | AD27: U | AE27: 2239091 | AF27: DIEM_NGUYEN | AG27: 0918496084 | AH27: 1390931 | AI27: =VLOOKUP(Sales[[#This Row],[Store]],'Store lay bao cao'!A:B,2,0) -> Lấy BC | AJ27: =VLOOKUP(Sales[[#This Row],[Associate]],'Associate Status'!B:C,2,0) -> Retired
A28: 2019 | B28: 9 | C28: 35 | D28: SS18 | E28: BRACELET | F28: SS18 | G28: 2268629 | H28: 2232000 | I28: 43709 | J28: 117930 | K28: RHN3079 | L28: ROSA MARIA | M28: RHN | N28: WACC | O28: 3079 | P28: 1 | Q28: Credit Card | R28: 6480000 | S28: 5890909 | T28: 0 | U28: 0 | V28: 0 | W28: Ngoc_Nguyen | X28: RM SILVER ROUND BRACELET-QUEUE END SET WITH (1)BLACK DIAMOND | Y28: Mrs. Le Thi Hoa | Z28: BR/PENNA(2) DIX (BLK (Q)) | AA28: 14 | AB28: SILVER/BLACK | AC28: 6480000 | AD28: S | AE28: 5890909 | AF28: HUE_BUI | AG28: 0913221545 | AH28: 3622280 | AI28: =VLOOKUP(Sales[[#This Row],[Store]],'Store lay bao cao'!A:B,2,0) -> Lấy BC | AJ28: =VLOOKUP(Sales[[#This Row],[Associate]],'Associate Status'!B:C,2,0) -> Active
A29: 2019 | B29: 10 | C29: 40 | D29: SS18 | E29: EARRINGS | F29: SS18 | G29: 6428160 | H29: 6428160 | I29: 43740 | J29: 117917 | K29: RHN3285 | L29: ROSA MARIA | M29: RHN | N29: WACC | O29: 3285 | P29: 1 | Q29: Credit Card | R29: 18663000 | S29: 16966364 | T29: 0 | U29: 0 | V29: 0 | W29: Ngoc_Nguyen | X29: RM SILVER DROP EARRINGS SET WITH ROSECUT DIAMONDS | Y29: Mrs. Tran Thanh Ly | Z29: BO TINA DIA (8X8) | AA29: 13 | AB29: SILVER/ROSEC | AC29: 18663000 | AD29: U | AE29: 16966364 | AF29: CHINH_NGUYEN | AG29: 0983861971 | AH29: 10538204 | AI29: =VLOOKUP(Sales[[#This Row],[Store]],'Store lay bao cao'!A:B,2,0) -> Lấy BC | AJ29: =VLOOKUP(Sales[[#This Row],[Associate]],'Associate Status'!B:C,2,0) -> Active
A30: 2019 | B30: 10 | C30: 40 | D30: SS17 | E30: JEWELRY | F30: SS17 | G30: 20619638 | H30: 15956500 | I30: 43743 | J30: 108993 | K30: RWR1784 | L30: SPINELLI KILCOLLIN | M30: RWR | N30: WACC | O30: 1784 | P30: 1 | Q30: Credit Card | R30: 41125000 | S30: 37386364 | T30: 0 | U30: 0 | V30: 0 | W30: Hang_Nguyen | X30: SPK Raneth 3 linked rings in sterling silver and 18k yellow and rose gold with mixed gold connectors and rose gold accents | Y30: Mr. Nguyen Hoang Tu | Z30: SG2-R-G3SRGYGRGAL | AA30: 14 | AB30: Rose gold, Gold | AC30: 41125000 | AD30: 5.5 | AE30: 37386364 | AF30: HUY_DUONG | AG30: 0849818415 | AH30: 16766726 | AI30: =VLOOKUP(Sales[[#This Row],[Store]],'Store lay bao cao'!A:B,2,0) -> Lấy BC | AJ30: =VLOOKUP(Sales[[#This Row],[Associate]],'Associate Status'!B:C,2,0) -> Retired
A31: 2019 | B31: 12 | C31: 48 | D31: FW11 | E31: JEWELRY | F31: FW11 | G31: 6009974 | H31: 6009974.1 | I31: 43800 | J31: 30028 | K31: RHN3903 | L31: ROSA MARIA | M31: RHN | N31: WACC | O31: 3903 | P31: 1 | Q31: Credit Card | R31: 21456000 | S31: 19505455 | T31: 0 | U31: 0 | V31: 0 | W31: Phuong_Bui | X31: RM Silver Ring - Top Silver treated Gages set w.icy Diamonds | Y31: Mrs. Le Thu Ngan | Z31: YESSIRA S-ST DIA ICY | AA31: 14 | AB31: Silver/Icy | AC31: 21456000 | AD31: 10 | AE31: 19505455 | AF31: SON_NGUYENVAN_SALE | AG31: 0983352011 | AH31: 13495481 | AI31: =VLOOKUP(Sales[[#This Row],[Store]],'Store lay bao cao'!A:B,2,0) -> Lấy BC | AJ31: =VLOOKUP(Sales[[#This Row],[Associate]],'Associate Status'!B:C,2,0) -> #N/A
A32: 2019 | B32: 12 | C32: 48 | D32: FW11 | E32: JEWELRY | F32: FW11 | G32: 5316516 | H32: 5316515.5 | I32: 43800 | J32: 30031 | K32: RHN3903 | L32: ROSA MARIA | M32: RHN | N32: WACC | O32: 3903 | P32: 1 | Q32: Credit Card | R32: 18980000 | S32: 17254545 | T32: 0 | U32: 0 | V32: 0 | W32: Phuong_Bui | X32: RM Siver Ring - Top Line Set w.Rosecut Diamond | Y32: Mrs. Le Thu Ngan | Z32: LARA DIA 8x8 | AA32: 14 | AB32: Silver/Rose | AC32: 18980000 | AD32: 11 | AE32: 17254545 | AF32: SON_NGUYENVAN_SALE | AG32: 0983352011 | AH32: 11938029 | AI32: =VLOOKUP(Sales[[#This Row],[Store]],'Store lay bao cao'!A:B,2,0) -> Lấy BC | AJ32: =VLOOKUP(Sales[[#This Row],[Associate]],'Associate Status'!B:C,2,0) -> #N/A
A33: 2019 | B33: 12 | C33: 48 | D33: FW11 | E33: JEWELRY | F33: FW11 | G33: 0 | H33: 5501437.8 | I33: 43800 | J33: 30032 | K33: RHN3903 | L33: ROSA MARIA | M33: RHN | N33: WACC | O33: 3903 | P33: 1 | Q33: Credit Card | R33: 19641000 | S33: 17855455 | T33: 0 | U33: 0 | V33: 0 | W33: Phuong_Bui | X33: RM Silver Ring - Top Silver treated Gages set w.Rubis | Y33: Mrs. Le Thu Ngan | Z33: YESSIRA S-ST DIA RU | AA33: 14 | AB33: Silver/Ruby | AC33: 19641000 | AD33: 10 | AE33: 17855455 | AF33: SON_NGUYENVAN_SALE | AG33: 0983352011 | AH33: 17855455 | AI33: =VLOOKUP(Sales[[#This Row],[Store]],'Store lay bao cao'!A:B,2,0) -> Lấy BC | AJ33: =VLOOKUP(Sales[[#This Row],[Associate]],'Associate Status'!B:C,2,0) -> #N/A
A34: 2019 | B34: 12 | C34: 53 | D34: SS13 | E34: JEWELRY | F34: SS13 | G34: 9714650 | H34: 9714649.8 | I34: 43830 | J34: 52834 | K34: RWR2285 | L34: ROSA MARIA | M34: RWR | N34: WACC | O34: 2285 | P34: 1 | Q34: Credit Card | R34: 32379000 | S34: 29435455 | T34: 0 | U34: 0 | V34: 0 | W34: Hang_Nguyen | X34: RM Silver ring-top (1 1/2mm) silver treated frame set with rubis-middle concave set paving with icy grey diamonds | Y34: Mrs. Phan Lan Phuong | Z34: BEENU(TB)S-ST C1 1/2 DIA (RU-IC | AA34: 19 | AB34: Silver/rubis/gre | AC34: 32379000 | AD34: 11 | AE34: 29435455 | AF34: CHI_NGUYEN | AH34: 19720805 | AI34: =VLOOKUP(Sales[[#This Row],[Store]],'Store lay bao cao'!A:B,2,0) -> Lấy BC | AJ34: =VLOOKUP(Sales[[#This Row],[Associate]],'Associate Status'!B:C,2,0) -> Retired
A35: 2020 | B35: 2 | C35: 5 | D35: SS12 | E35: JEWELRY | F35: SS12 | G35: 6573600 | H35: 6573600 | I35: 43863 | J35: 37108 | K35: RHN4665 | L35: ROSA MARIA | M35: RHN | N35: WACC | O35: 4665 | P35: 1 | Q35: Credit Card | R35: 24586000 | S35: 22350909 | T35: 0 | U35: 0 | V35: 0 | W35: Ngoc_Nguyen | X35: RM Silver treated ring-top framed with rubis-middle smoky quartz | Y35: Mrs. Le Thu Ngan | Z35: BEENU R (TB)ST DIA (RU-QUARTZ) | AA35: 11 | AB35: SILVER | AC35: 24586000 | AD35: 11 | AE35: 22350909 | AF35: HOA_TRAN | AG35: 0983352011 | AH35: 15777309 | AI35: =VLOOKUP(Sales[[#This Row],[Store]],'Store lay bao cao'!A:B,2,0) -> Lấy BC | AJ35: =VLOOKUP(Sales[[#This Row],[Associate]],'Associate Status'!B:C,2,0) -> Retired
A36: 2020 | B36: 2 | C36: 5 | D36: SS12 | E36: JEWELRY | F36: SS12 | G36: 4712400 | H36: 6490260 | I36: 43863 | J36: 37083 | K36: RHN4665 | L36: ROSA MARIA | M36: RHN | N36: WACC | O36: 4665 | P36: 1 | Q36: Credit Card | R36: 17625000 | S36: 16022727 | T36: 0 | U36: 0 | V36: 0 | W36: Ngoc_Nguyen | X36: RM Silver treated ring-top silver treated frame-middle curved silver polish | Y36: Mrs. Le Thu Ngan | Z36: BEGUM R (TB)ST-ST-S | AA36: 11 | AB36: SILVER | AC36: 17625000 | AD36: 10 | AE36: 16022727 | AF36: HOA_TRAN | AG36: 0983352011 | AH36: 11310327 | AI36: =VLOOKUP(Sales[[#This Row],[Store]],'Store lay bao cao'!A:B,2,0) -> Lấy BC | AJ36: =VLOOKUP(Sales[[#This Row],[Associate]],'Associate Status'!B:C,2,0) -> Retired
A37: 2020 | B37: 2 | C37: 6 | D37: FW11 | E37: JEWELRY | F37: FW11 | G37: 5316516 | H37: 5316515.5 | I37: 43868 | J37: 30030 | K37: RHN4703 | L37: ROSA MARIA | M37: RHN | N37: WACC | O37: 4703 | P37: 1 | Q37: Check | R37: 18031000 | S37: 16391818 | T37: 5 | U37: 862727 | V37: 949000 | W37: Ngoc_Nguyen | X37: RM Siver Ring - Top Line Set w.Rosecut Diamond | Y37: Ms. To Thi Hanh | Z37: LARA DIA 8x8 | AA37: 17 | AB37: Silver/Rose | AC37: 18980000 | AD37: 10 | AE37: 17254545 | AF37: HUYEN_DANG | AG37: 0916671961 | AH37: 11075302 | AI37: =VLOOKUP(Sales[[#This Row],[Store]],'Store lay bao cao'!A:B,2,0) -> Lấy BC | AJ37: =VLOOKUP(Sales[[#This Row],[Associate]],'Associate Status'!B:C,2,0) -> Active
A38: 2020 | B38: 2 | C38: 6 | D38: SS18 | E38: BRACELET | F38: SS18 | G38: 4196160 | H38: 4196160 | I38: 43868 | J38: 117926 | K38: RHN4703 | L38: ROSA MARIA | M38: RHN | N38: WACC | O38: 4703 | P38: 1 | Q38: Check | R38: 11573850 | S38: 10521682 | T38: 5 | U38: 553773 | V38: 609150 | W38: Ngoc_Nguyen | X38: RM SILVER ROUND BRACELET-TOP SILVER FRAME SET WITH ICY GREY DIAMONDS-QUEUE END SET WITH RUBIS | Y38: Ms. To Thi Hanh | Z38: BR/TOKO (1) (V) DIX (ICY GRIS T | AA38: 17 | AB38: ICY GREY/RUB | AC38: 12183000 | AD38: S | AE38: 11075455 | AF38: HUYEN_DANG | AG38: 0916671961 | AH38: 6325522 | AI38: =VLOOKUP(Sales[[#This Row],[Store]],'Store lay bao cao'!A:B,2,0) -> Lấy BC | AJ38: =VLOOKUP(Sales[[#This Row],[Associate]],'Associate Status'!B:C,2,0) -> Active
A39: 2020 | B39: 2 | C39: 6 | D39: SS17 | E39: JEWELRY | F39: SS17 | G39: 43211883 | H39: 33628500 | I39: 43868 | J39: 109934 | K39: RHN4707 | L39: NAK ARMSTRONG | M39: RHN | N39: WACC | O39: 4707 | P39: 1 | Q39: Credit Card | R39: 93413000 | S39: 84920909 | T39: 0 | U39: 0 | V39: 0 | W39: Ngoc_Nguyen | X39: NAK PENDANT: ONE-OF-A-KIND RUBY, PINK TOURMALINE, RECYCLED 18K ROSE GOLD, AND OXIDIZED STERLING SILVER; 18" IN LENGTH | Y39: Ms. Nguyen thu Cuc | Z39: 30013-OAK2-18SS | AA39: 18 | AB39: ROSE GOLD | AC39: 93413000 | AD39: U | AE39: 84920909 | AF39: KIEUDIEM_NGUYEN | AG39: 0913022326 | AH39: 41709026 | AI39: =VLOOKUP(Sales[[#This Row],[Store]],'Store lay bao cao'!A:B,2,0) -> Lấy BC | AJ39: =VLOOKUP(Sales[[#This Row],[Associate]],'Associate Status'!B:C,2,0) -> #N/A
A40: 2020 | B40: 3 | C40: 13 | D40: SS17 | E40: JEWELRY | F40: SS17 | G40: -42124791 | H40: -32782500 | I40: 43913 | J40: 109922 | K40: RWR2672 | L40: NAK ARMSTRONG | M40: RWR | N40: WACC | O40: 2672 | P40: -1 | Q40: Credit Card | R40: -91063000 | S40: -82784545 | T40: 0 | U40: 0 | V40: 0 | W40: Hang_Nguyen | X40: NAK STUDS: 1.84CTS RECLAIMED MOGHUL-CUT BLACK DIAMOND, 0.48CTS PRINCESS-CUT WHITE DIAMOND AND RECYCLED 20K ROSE GOLD; 9.6MM IN DIAMETER; 7MM IN DIAMETER | Y40: Mrs. Pham Thi Huong | Z40: 10290-BD-20R | AA40: 19 | AB40: ROSE GOLD | AC40: -91063000 | AD40: U | AE40: -82784545 | AF40: CHI_NGUYEN | AG40: 0906328888 | AH40: -40659754 | AI40: =VLOOKUP(Sales[[#This Row],[Store]],'Store lay bao cao'!A:B,2,0) -> Lấy BC | AJ40: =VLOOKUP(Sales[[#This Row],[Associate]],'Associate Status'!B:C,2,0) -> Retired
A41: 2020 | B41: 3 | C41: 13 | D41: SS17 | E41: JEWELRY | F41: SS17 | G41: 42124791 | H41: 32782500 | I41: 43913 | J41: 109922 | K41: RWR2668 | L41: NAK ARMSTRONG | M41: RWR | N41: WACC | O41: 2668 | P41: 1 | Q41: Credit Card | R41: 91063000 | S41: 82784545 | T41: 0 | U41: 0 | V41: 0 | W41: Ha_Nguyen | X41: NAK STUDS: 1.84CTS RECLAIMED MOGHUL-CUT BLACK DIAMOND, 0.48CTS PRINCESS-CUT WHITE DIAMOND AND RECYCLED 20K ROSE GOLD; 9.6MM IN DIAMETER; 7MM IN DIAMETER | Y41: Mrs. Pham Thi Huong | Z41: 10290-BD-20R | AA41: 11 | AB41: ROSE GOLD | AC41: 91063000 | AD41: U | AE41: 82784545 | AF41: CHI_NGUYEN | AG41: 0906328888 | AH41: 40659754 | AI41: =VLOOKUP(Sales[[#This Row],[Store]],'Store lay bao cao'!A:B,2,0) -> Lấy BC | AJ41: =VLOOKUP(Sales[[#This Row],[Associate]],'Associate Status'!B:C,2,0) -> Retired
A42: 2020 | B42: 10 | C42: 42 | D42: FW12 | E42: JEWELRY | F42: FW12 | G42: 17531100 | H42: 17531100 | I42: 44117 | J42: 42534 | K42: RHN6302 | L42: ROSA MARIA | M42: RHN | N42: WACC | O42: 6302 | P42: 1 | Q42: Account | R42: 58437000 | S42: 53124545 | T42: 0 | U42: 0 | V42: 0 | W42: Ngoc_Nguyen | X42: RM Silver ring-top (1 1/2mm)silver treated frame set with rubis-middle topaz | Y42: Tran Thuy Chi | Z42: JUNYA(V) S-ST C1 1/2 DIA(RU-TOP | AA42: 10 | AB42: SILVER | AC42: 58437000 | AD42: 11 | AE42: 53124545 | AF42: KIEUDIEM_NGUYEN | AG42: 0982928535 | AH42: 35593445 | AI42: =VLOOKUP(Sales[[#This Row],[Store]],'Store lay bao cao'!A:B,2,0) -> Lấy BC | AJ42: =VLOOKUP(Sales[[#This Row],[Associate]],'Associate Status'!B:C,2,0) -> #N/A
A43: 2020 | B43: 10 | C43: 42 | D43: FW17 | E43: JEWELRY | F43: FW17 | G43: 30000000 | H43: 0 | I43: 44120 | J43: 116329 | K43: GIF134 | L43: Ted Muehling | M43: GIF | N43: WACC | O43: 134 | P43: 1 | Q43: None | R43: 0 | S43: 0 | T43: 100 | U43: 27272727 | V43: 30000000 | W43: Oanh_Do | X43: TM SNAIL CHOKER 14KY NECKLACE (GOLD) | Y43: GLOBAL LINK CORPORATION | Z43: SNAIL CHOKER 14KY | AA43: 10 | AC43: 30000000 | AD43: U | AE43: 27272727 | AF43: SYSADMIN | AH43: -30000000 | AI43: =VLOOKUP(Sales[[#This Row],[Store]],'Store lay bao cao'!A:B,2,0) -> Không lấy BC | AJ43: =VLOOKUP(Sales[[#This Row],[Associate]],'Associate Status'!B:C,2,0) -> Retired
A44: 2020 | B44: 10 | C44: 42 | D44: SS17 | E44: JEWELRY | F44: SS17 | G44: 13991896 | H44: 10827625 | I44: 44120 | J44: 109008 | K44: LOA135 | L44: SPINELLI KILCOLLIN | M44: LOA | N44: WACC | O44: 135 | P44: 1 | Q44: Check | R44: 27907000 | S44: 25370000 | T44: 0 | U44: 0 | V44: 0 | W44: Oanh_Do | X44: SPK Sirius SG Single band of sterling silver with 18k yellow gold accents and micro-pavé black diamonds | Y44: Mrs. Bui Lan | Z44: SG12-R-G4S2YGAPCG | AA44: 15 | AB44: GOLD | AC44: 27907000 | AD44: 6.5 | AE44: 25370000 | AF44: SYSADMIN | AG44: 0903751574 | AH44: 11378104 | AI44: =VLOOKUP(Sales[[#This Row],[Store]],'Store lay bao cao'!A:B,2,0) -> Không lấy BC | AJ44: =VLOOKUP(Sales[[#This Row],[Associate]],'Associate Status'!B:C,2,0) -> Retired
A45: 2020 | B45: 10 | C45: 44 | D45: SS18 | E45: RING | F45: SS18 | G45: 6026400 | H45: 6026400 | I45: 44132 | J45: 117957 | K45: LOA136 | L45: ROSA MARIA | M45: LOA | N45: WACC | O45: 136 | P45: 1 | Q45: Account | R45: 6026392.2 | S45: 5478538 | T45: 65.56 | U45: 10426916 | V45: 11469608 | W45: Oanh_Do | X45: RM SILVER RING INTO 2:(1)TOP 18KT PINK GOLD FLAT LEAF (1)SILVER FRAME-MIDDLE WHITE SAPPHIRE | Y45: Mrs. Tran Thi Hoai Anh | Z45: NOUFA (4)S-GP-S DIX (SA.BLANC) | AA45: 11 | AB45: PINK GOLD/WH | AC45: 17496000 | AD45: 11 | AE45: 15905455 | AF45: SYSADMIN | AG45: 0908039899 | AH45: -547862 | AI45: =VLOOKUP(Sales[[#This Row],[Store]],'Store lay bao cao'!A:B,2,0) -> Không lấy BC | AJ45: =VLOOKUP(Sales[[#This Row],[Associate]],'Associate Status'!B:C,2,0) -> Retired
A46: 2020 | B46: 10 | C46: 44 | D46: SS18 | E46: RING | F46: SS18 | G46: 7365600 | H46: 7365600 | I46: 44132 | J46: 117959 | K46: LOA136 | L46: ROSA MARIA | M46: LOA | N46: WACC | O46: 136 | P46: 1 | Q46: Account | R46: 7365718.8 | S46: 6696108 | T46: 65.55 | U46: 12743892 | V46: 14018281 | W46: Oanh_Do | X46: RM SILVER TWISTED BELL FLOWER RING-TOP SILVER-MIDDLE silver | Y46: Mrs. Tran Thi Hoai Anh | Z46: SAXO (4) S-S-S | AA46: 11 | AB46: SILVER | AC46: 21384000 | AD46: 12 | AE46: 19440000 | AF46: SYSADMIN | AG46: 0908039899 | AH46: -669492 | AI46: =VLOOKUP(Sales[[#This Row],[Store]],'Store lay bao cao'!A:B,2,0) -> Không lấy BC | AJ46: =VLOOKUP(Sales[[#This Row],[Associate]],'Associate Status'!B:C,2,0) -> Retired
A47: 2021 | B47: 1 | C47: 3 | D47: SS18 | E47: EARRINGS | F47: SS18 | G47: 848160 | H47: 848160 | I47: 44210 | J47: 117922 | K47: RWR3812 | L47: ROSA MARIA | M47: RWR | N47: WACC | O47: 3812 | P47: 1 | Q47: Split | R47: 2463000 | S47: 2239091 | T47: 0 | U47: 0 | V47: 0 | W47: Ha_Nguyen | X47: RM SILVER STUDS FLOWERS EARRINGS | Y47: Ms. Luu Thi Thuy Linh | Z47: BO NILOUFAR (3)(D) | AA47: 14 | AB47: SILVER | AC47: 2463000 | AD47: U | AE47: 2239091 | AF47: SYSADMIN | AG47: 0938335357 | AH47: 1390931 | AI47: =VLOOKUP(Sales[[#This Row],[Store]],'Store lay bao cao'!A:B,2,0) -> Lấy BC | AJ47: =VLOOKUP(Sales[[#This Row],[Associate]],'Associate Status'!B:C,2,0) -> Retired
A48: 2021 | B48: 1 | C48: 3 | D48: FW16 | E48: JEWELRY | F48: FW16 | G48: 2284200 | H48: 2284200 | I48: 44212 | J48: 90589 | K48: RWR3823 | L48: ROSA MARIA | M48: RWR | N48: WACC | O48: 3823 | P48: 1 | Q48: Credit Card | R48: 7614000 | S48: 6921818 | T48: 0 | U48: 0 | V48: 0 | W48: Ha_Nguyen | X48: RM SILVER SNAKE RING(Mat) | Y48: Mrs. Nguyen Thi Thuc Anh | Z48: PENN | AA48: 20 | AC48: 7614000 | AD48: 13 | AE48: 6921818 | AF48: LINH_LUU | AG48: 0903017249 | AH48: 4637618 | AI48: =VLOOKUP(Sales[[#This Row],[Store]],'Store lay bao cao'!A:B,2,0) -> Lấy BC | AJ48: =VLOOKUP(Sales[[#This Row],[Associate]],'Associate Status'!B:C,2,0) -> Active
A49: 2021 | B49: 1 | C49: 5 | D49: FW17 | E49: JEWELRY | F49: FW17 | G49: 12102500 | H49: 12102500 | I49: 44223 | J49: 117905 | K49: RHN7226 | L49: ROSA MARIA | M49: RHN | N49: WACC | O49: 7226 | P49: 1 | Q49: Split | R49: 36308000 | S49: 33007273 | T49: 0 | U49: 0 | V49: 0 | W49: Huyen_Dang | X49: RM EARRINGS | Y49: Le Thi Hong Hong | Z49: BO ATOLL(D) DIA ICY CRIS+ B(S) | AA49: 18 | AB49: ICY GRIS | AC49: 36308000 | AD49: U | AE49: 33007273 | AF49: HUYEN_DANG | AG49: 0982610062 | AH49: 20904773 | AI49: =VLOOKUP(Sales[[#This Row],[Store]],'Store lay bao cao'!A:B,2,0) -> Lấy BC | AJ49: =VLOOKUP(Sales[[#This Row],[Associate]],'Associate Status'!B:C,2,0) -> Active
A50: 2021 | B50: 2 | C50: 9 | D50: FW13 | E50: JEWELRY | F50: FW13 | G50: 8591400 | H50: 8591400 | I50: 44254 | J50: 53343 | K50: RHN7386 | L50: ROSA MARIA | M50: RHN | N50: WACC | O50: 7386 | P50: 1 | Q50: Credit Card | R50: 29593000 | S50: 26902727 | T50: 0 | U50: 0 | V50: 0 | W50: Ngoc_Nguyen | X50: RM SILVER RING-TOP SILVER TREATED BANGLE FRAMED WITH ICY GREY DIAMONDS | Y50: Mrs. Tran Thanh Ly | Z50: BIKRAM(V) S-ST DIX (ICY GRIS) | AA50: 14 | AB50: SILVER/GREY | AC50: 29593000 | AD50: 12 | AE50: 26902727 | AF50: HUE_BUI | AG50: 0983861971 | AH50: 18311327 | AI50: =VLOOKUP(Sales[[#This Row],[Store]],'Store lay bao cao'!A:B,2,0) -> Lấy BC | AJ50: =VLOOKUP(Sales[[#This Row],[Associate]],'Associate Status'!B:C,2,0) -> Active
A51: 2021 | B51: 2 | C51: 9 | D51: SS12 | E51: JEWELRY | F51: SS12 | G51: 4712400 | H51: 6490260 | I51: 44254 | J51: 37084 | K51: RHN7386 | L51: ROSA MARIA | M51: RHN | N51: WACC | O51: 7386 | P51: 1 | Q51: Credit Card | R51: 17625000 | S51: 16022727 | T51: 0 | U51: 0 | V51: 0 | W51: Ngoc_Nguyen | X51: RM Silver treated ring-top silver treated frame-middle curved silver polish | Y51: Mrs. Tran Thanh Ly | Z51: BEGUM R (TB)ST-ST-S | AA51: 14 | AB51: SILVER | AC51: 17625000 | AD51: 11 | AE51: 16022727 | AF51: HUE_BUI | AG51: 0983861971 | AH51: 11310327 | AI51: =VLOOKUP(Sales[[#This Row],[Store]],'Store lay bao cao'!A:B,2,0) -> Lấy BC | AJ51: =VLOOKUP(Sales[[#This Row],[Associate]],'Associate Status'!B:C,2,0) -> Active
A52: 2021 | B52: 3 | C52: 12 | D52: FW17 | E52: JEWELRY | F52: FW17 | G52: 34662000 | H52: 34662000 | I52: 44272 | J52: 116338 | K52: RWR4019 | L52: Ted Muehling | M52: RWR | N52: WACC | O52: 4019 | P52: 1 | Q52: Credit Card | R52: 47088000 | S52: 42807273 | T52: 0 | U52: 0 | V52: 0 | W52: Ha_Nguyen | X52: TM HEXAGONAL TRAPICHE TOURMALINE STUD EARRINGS 18K | Y52: Mrs. Tran Hai Anh | Z52: GK 478 | AA52: 19 | AB52: GREEN GOLD | AC52: 47088000 | AD52: U | AE52: 42807273 | AF52: HUONG_NGUYENKIM | AG52: 0912858889 | AH52: 8145273 | AI52: =VLOOKUP(Sales[[#This Row],[Store]],'Store lay bao cao'!A:B,2,0) -> Lấy BC | AJ52: =VLOOKUP(Sales[[#This Row],[Associate]],'Associate Status'!B:C,2,0) -> Active
A53: 2021 | B53: 5 | C53: 20 | D53: SS17 | E53: JEWELRY | F53: SS17 | G53: 13255481 | H53: 10257750 | I53: 44328 | J53: 108996 | K53: RWR4269 | L53: SPINELLI KILCOLLIN | M53: RWR | N53: WACC | O53: 4269 | P53: 1 | Q53: Credit Card | R53: 26438000 | S53: 24034545 | T53: 0 | U53: 0 | V53: 0 | W53: Ha_Nguyen | X53: SPK Orion 3 linked rings in silver with 18k gold connectors and accents | Y53: Ms. Truong An Phuong | Z53: SG2-R-G3SRGGAL | AA53: 12 | AB53: GOLD | AC53: 26438000 | AD53: 6 | AE53: 24034545 | AF53: HUONG_NGUYENKIM | AG53: 0968267157 | AH53: 10779064 | AI53: =VLOOKUP(Sales[[#This Row],[Store]],'Store lay bao cao'!A:B,2,0) -> Lấy BC | AJ53: =VLOOKUP(Sales[[#This Row],[Associate]],'Associate Status'!B:C,2,0) -> Active
A54: 2021 | B54: 5 | C54: 20 | D54: SS17 | E54: JEWELRY | F54: SS17 | G54: 7364157 | H54: 5698750 | I54: 44328 | J54: 108991 | K54: RWR4270 | L54: SPINELLI KILCOLLIN | M54: RWR | N54: WACC | O54: 4270 | P54: 1 | Q54: Credit Card | R54: 14688000 | S54: 13352727 | T54: 0 | U54: 0 | V54: 0 | W54: Ha_Nguyen | X54: SPK Raneth Silver 3 linked rings in sterlin silver with silver connectors and accents | Y54: Ms. Truong An Phuong | Z54: SG9-R-G3LSGA | AA54: 13 | AB54: SILVER | AC54: 14688000 | AD54: 6.5 | AE54: 13352727 | AF54: HUONG_NGUYENKIM | AG54: 0968267157 | AH54: 5988570 | AI54: =VLOOKUP(Sales[[#This Row],[Store]],'Store lay bao cao'!A:B,2,0) -> Lấy BC | AJ54: =VLOOKUP(Sales[[#This Row],[Associate]],'Associate Status'!B:C,2,0) -> Active
A55: 2021 | B55: 6 | C55: 25 | D55: FW16 | E55: JEWELRY | F55: FW16 | G55: 2030400 | H55: 2030400 | I55: 44366 | J55: 90562 | K55: RHN8070 | L55: ROSA MARIA | M55: RHN | N55: WACC | O55: 8070 | P55: 1 | Q55: Credit Card | R55: 6768000 | S55: 6152727 | T55: 0 | U55: 0 | V55: 0 | W55: Ngoc_Nguyen | X55: RM SILVER RING-TOP SILVER HEAD SET WITH (1) RUBIS | Y55: Mrs. Tran Thanh Ly | Z55: NEGIA DIX | AA55: 13 | AB55: RUBIS | AC55: 6768000 | AD55: 12 | AE55: 6152727 | AF55: CHINH_NGUYEN | AG55: 0983861971 | AH55: 4122327 | AI55: =VLOOKUP(Sales[[#This Row],[Store]],'Store lay bao cao'!A:B,2,0) -> Lấy BC | AJ55: =VLOOKUP(Sales[[#This Row],[Associate]],'Associate Status'!B:C,2,0) -> Active
A56: 2021 | B56: 6 | C56: 25 | D56: FW16 | E56: JEWELRY | F56: FW16 | G56: 3595500 | H56: 3595500 | I56: 44366 | J56: 90556 | K56: RHN8071 | L56: ROSA MARIA | M56: RHN | N56: WACC | O56: 8071 | P56: 1 | Q56: Credit Card | R56: 11985000 | S56: 10895455 | T56: 0 | U56: 0 | V56: 0 | W56: Ngoc_Nguyen | X56: RM SILVER RING-TOP SILVER TREATED HEAD SET WITH BLACK DIAMONDS | Y56: Mrs. Tran Thanh Ly | Z56: WOINA (R )S-ST DIX | AA56: 13 | AB56: BLACK | AC56: 11985000 | AD56: 13 | AE56: 10895455 | AF56: KIEUDIEM_NGUYEN | AG56: 0983861971 | AH56: 7299955 | AI56: =VLOOKUP(Sales[[#This Row],[Store]],'Store lay bao cao'!A:B,2,0) -> Lấy BC | AJ56: =VLOOKUP(Sales[[#This Row],[Associate]],'Associate Status'!B:C,2,0) -> #N/A
A57: 2021 | B57: 12 | C57: 52 | D57: FW16 | E57: JEWELRY | F57: FW16 | G57: 9475200 | H57: 9475200 | I57: 44552 | J57: 90573 | K57: LOA199 | L57: ROSA MARIA | M57: LOA | N57: WACC | O57: 199 | P57: 1 | Q57: None | R57: 0 | S57: 0 | T57: 100 | U57: 28712727 | V57: 31584000 | W57: thu_trang | X57: RM TWISTED SILVER SNAKE RING-HEAD SILVER TREATED FRAME SET WITH ICY GREY DIAMONDS-MIDDLE SILVER | Y57: GLOBAL LINK CORPORATION | Z57: TOKO (3)(VP)(TW)S-ST-S DIX | AA57: 15 | AB57: ICY GRIS(2) | AC57: 31584000 | AD57: 12 | AE57: 28712727 | AF57: THU_TRANG | AH57: -9475200 | AI57: =VLOOKUP(Sales[[#This Row],[Store]],'Store lay bao cao'!A:B,2,0) -> Không lấy BC | AJ57: =VLOOKUP(Sales[[#This Row],[Associate]],'Associate Status'!B:C,2,0) -> #N/A
A58: 2021 | B58: 12 | C58: 52 | D58: FW16 | E58: JEWELRY | F58: FW16 | G58: 9771300 | H58: 9771300 | I58: 44552 | J58: 90572 | K58: LOA199 | L58: ROSA MARIA | M58: LOA | N58: WACC | O58: 199 | P58: 1 | Q58: None | R58: 0 | S58: 0 | T58: 100 | U58: 29610000 | V58: 32571000 | W58: thu_trang | X58: RM TWISTED SILVER ROUND RING-TOP SILVER TREATED FRAME SET WITH ICY GREY DIAMONDS-MIDDLE SMOKY QUARTZ | Y58: GLOBAL LINK CORPORATION | Z58: TOVE(5)(TW) S-ST DIA | AA58: 15 | AB58: ICY GRIS(1)-S.QT | AC58: 32571000 | AD58: 12 | AE58: 29610000 | AF58: THU_TRANG | AH58: -9771300 | AI58: =VLOOKUP(Sales[[#This Row],[Store]],'Store lay bao cao'!A:B,2,0) -> Không lấy BC | AJ58: =VLOOKUP(Sales[[#This Row],[Associate]],'Associate Status'!B:C,2,0) -> #N/A
A59: 2022 | B59: 1 | C59: 3 | D59: SS17 | E59: JEWELRY | F59: SS17 | G59: 13255481 | H59: 10257750 | I59: 44574 | J59: 108999 | K59: RWR4724 | L59: SPINELLI KILCOLLIN | M59: RWR | N59: WACC | O59: 4724 | P59: 1 | Q59: Split | R59: 26438000 | S59: 24034545 | T59: 0 | U59: 0 | V59: 0 | W59: Nghia_Nguyen | X59: SPK Orion 3 linked rings in silver with 18k gold connectors and accents | Y59: Mrs. Le Thu Ngan | Z59: SG2-R-G3SRGGAL | AA59: 13 | AB59: GOLD | AC59: 26438000 | AD59: 7.5 | AE59: 24034545 | AF59: TRANG_TRAN | AG59: 0983352011 | AH59: 10779064 | AI59: =VLOOKUP(Sales[[#This Row],[Store]],'Store lay bao cao'!A:B,2,0) -> Lấy BC | AJ59: =VLOOKUP(Sales[[#This Row],[Associate]],'Associate Status'!B:C,2,0) -> Retired
A60: 2022 | B60: 2 | C60: 7 | D60: SS18 | E60: RING | F60: SS18 | G60: 6026400 | H60: 6026400 | I60: 44604 | J60: 117947 | K60: RWR4911 | L60: ROSA MARIA | M60: RWR | N60: WACC | O60: 4911 | P60: 1 | Q60: Credit Card | R60: 15746400 | S60: 14580000 | T60: 10 | U60: 1620000 | V60: 1749600 | W60: Ha_Nguyen | X60: RM SILVER RING-TOP SILVER TREATED FRAME SET WITH ICY GREY DIAMONDS-MIDDLE LEMON QUARTZ | Y60: Mrs. Duong Quynh Huong | Z60: BEENU(TH)S-ST DIA (ICY GRIS-LEM | AA60: 16 | AB60: ICY GREY/LEM | AC60: 17496000 | AD60: 12 | AE60: 16200000 | AF60: LINH_LUU | AG60: 0937369369 | AH60: 8553600 | AI60: =VLOOKUP(Sales[[#This Row],[Store]],'Store lay bao cao'!A:B,2,0) -> Lấy BC | AJ60: =VLOOKUP(Sales[[#This Row],[Associate]],'Associate Status'!B:C,2,0) -> Active
A61: 2022 | B61: 2 | C61: 8 | D61: SS18 | E61: EARRINGS | F61: SS18 | G61: 16293600 | H61: 16293600 | I61: 44606 | J61: 117918 | K61: RHN9184 | L61: ROSA MARIA | M61: RHN | N61: WACC | O61: 9184 | P61: 1 | Q61: Credit Card | R61: 42573600 | S61: 39420000 | T61: 10 | U61: 4380000 | V61: 4730400 | W61: Nghia_Nguyen | X61: RM 18KT YELLOW GOLD DROP EARRING-TOP 18KT YELLOW GOLD BANGLE SET WITH ICY GREY DIAMONDS- MIDDLE SMOKY QUARTZ(Transparent) | Y61: Ms. Pham Thi Cam Ly | Z61: BO 113 (V)GY DIA (ICY GRIS-S.QT | AA61: 13 | AB61: YELLOW GOLD/ | AC61: 47304000 | AD61: U | AE61: 43800000 | AF61: HUYEN_DANG | AG61: 0913212299 | AH61: 23126400 | AI61: =VLOOKUP(Sales[[#This Row],[Store]],'Store lay bao cao'!A:B,2,0) -> Lấy BC | AJ61: =VLOOKUP(Sales[[#This Row],[Associate]],'Associate Status'!B:C,2,0) -> Active
A62: 2022 | B62: 4 | C62: 16 | D62: FW16 | E62: JEWELRY | F62: FW16 | G62: -9771300 | H62: -9771300 | I62: 44664 | J62: 90572 | K62: LOA290 | L62: ROSA MARIA | M62: LOA | N62: WACC | O62: 290 | P62: -1 | Q62: None | R62: 0 | S62: 0 | T62: 100 | U62: -30158333 | V62: -32571000 | W62: son_tran | X62: RM TWISTED SILVER ROUND RING-TOP SILVER TREATED FRAME SET WITH ICY GREY DIAMONDS-MIDDLE SMOKY QUARTZ | Y62: GLOBAL LINK CORPORATION | Z62: TOVE(5)(TW) S-ST DIA | AA62: 10 | AB62: ICY GRIS(1)-S.QT | AC62: -32571000 | AD62: 12 | AE62: -30158333 | AF62: THU_TRANG | AH62: 9771300 | AI62: =VLOOKUP(Sales[[#This Row],[Store]],'Store lay bao cao'!A:B,2,0) -> Không lấy BC | AJ62: =VLOOKUP(Sales[[#This Row],[Associate]],'Associate Status'!B:C,2,0) -> #N/A
A63: 2022 | B63: 4 | C63: 16 | D63: FW16 | E63: JEWELRY | F63: FW16 | G63: -9475200 | H63: -9475200 | I63: 44664 | J63: 90573 | K63: LOA289 | L63: ROSA MARIA | M63: LOA | N63: WACC | O63: 289 | P63: -1 | Q63: None | R63: 0 | S63: 0 | T63: 100 | U63: -29244444 | V63: -31584000 | W63: son_tran | X63: RM TWISTED SILVER SNAKE RING-HEAD SILVER TREATED FRAME SET WITH ICY GREY DIAMONDS-MIDDLE SILVER | Y63: GLOBAL LINK CORPORATION | Z63: TOKO (3)(VP)(TW)S-ST-S DIX | AA63: 10 | AB63: ICY GRIS(2) | AC63: -31584000 | AD63: 12 | AE63: -29244444 | AF63: THU_TRANG | AH63: 9475200 | AI63: =VLOOKUP(Sales[[#This Row],[Store]],'Store lay bao cao'!A:B,2,0) -> Không lấy BC | AJ63: =VLOOKUP(Sales[[#This Row],[Associate]],'Associate Status'!B:C,2,0) -> #N/A
A64: 2022 | B64: 4 | C64: 18 | D64: SS12 | E64: JEWELRY | F64: SS12 | G64: 6177600 | H64: 6177600 | I64: 44676 | J64: 37073 | K64: RHN174 | L64: ROSA MARIA | M64: RHN | N64: WACC | O64: 174 | P64: 1 | Q64: Credit Card | R64: 23105000 | S64: 21393519 | T64: 0 | U64: 0 | V64: 0 | W64: Ngoc_Nguyen | X64: RM Silver treated ring-top middle blue sapphire | Y64: Mrs. Tran Thanh Ly | Z64: BELQUIS R (TH)ST DIX | AA64: 15 | AB64: Silver/blue | AC64: 23105000 | AD64: 10 | AE64: 21393519 | AF64: CHINH_NGUYEN | AG64: 0983861971 | AH64: 15215919 | AI64: =VLOOKUP(Sales[[#This Row],[Store]],'Store lay bao cao'!A:B,2,0) -> Lấy BC | AJ64: =VLOOKUP(Sales[[#This Row],[Associate]],'Associate Status'!B:C,2,0) -> Active
A65: 2022 | B65: 5 | C65: 21 | D65: SS17 | E65: JEWELRY | F65: SS17 | G65: -26510963 | H65: -20515500 | I65: 44700 | J65: 109005 | K65: GIF297 | L65: SPINELLI KILCOLLIN | M65: GIF | N65: WACC | O65: 297 | P65: -1 | Q65: None | R65: 0 | S65: 0 | T65: 100 | U65: -48958333 | V65: -52875000 | W65: son_tran | X65: SPK Libra SG 3 linked rings in silver with yellow gold connectors and micro-pave grey diamonds | Y65: Cong ty Globallink | Z65: SG12-R-G3MXMMXGC | AA65: 14 | AB65: GOLD | AC65: -52875000 | AD65: 7 | AE65: -48958333 | AF65: SYSADMIN | AH65: 26510963 | AI65: =VLOOKUP(Sales[[#This Row],[Store]],'Store lay bao cao'!A:B,2,0) -> Không lấy BC | AJ65: =VLOOKUP(Sales[[#This Row],[Associate]],'Associate Status'!B:C,2,0) -> Retired
A66: 2022 | B66: 7 | C66: 28 | D66: FW22 | E66: NECKLACE | F66: FW22 | G66: 1641228 | H66: 1430750 | I66: 44748 | J66: 174875 | K66: RWR5495 | L66: GEODE | M66: RWR | N66: WACC | O66: 5495 | P66: 1 | Q66: Debit Card | R66: 7168500 | S66: 6637500 | T66: 10 | U66: 737500 | V66: 796500 | W66: Nghia_Nguyen | X66: GEO - NECKLACE AMETHIST | Y66: Ms. Le Thi Thuy Hanh | Z66: E4 | AA66: 13 | AB66: VIOLET | AC66: 7965000 | AD66: UN | AE66: 7375000 | AF66: TRANG_TRAN | AG66: 0903288262 | AH66: 4996272 | AI66: =VLOOKUP(Sales[[#This Row],[Store]],'Store lay bao cao'!A:B,2,0) -> Lấy BC | AJ66: =VLOOKUP(Sales[[#This Row],[Associate]],'Associate Status'!B:C,2,0) -> Retired
A67: 2022 | B67: 7 | C67: 29 | D67: FW22 | E67: NECKLACE | F67: FW22 | G67: 1279142 | H67: 1115100 | I67: 44754 | J67: 174869 | K67: RHN580 | L67: GEODE | M67: RHN | N67: WACC | O67: 580 | P67: 1 | Q67: Split | R67: 5575500 | S67: 5162500 | T67: 10 | U67: 573611 | V67: 619500 | W67: Ngoc_Nguyen | X67: GEO - NECKLACE PEARL | Y67: Ms. To Thi Hanh | Z67: D2 | AA67: 18 | AB67: WHITE | AC67: 6195000 | AD67: UN | AE67: 5736111 | AF67: NGHIA_NGUYENHN | AG67: 0916671961 | AH67: 3883358 | AI67: =VLOOKUP(Sales[[#This Row],[Store]],'Store lay bao cao'!A:B,2,0) -> Lấy BC | AJ67: =VLOOKUP(Sales[[#This Row],[Associate]],'Associate Status'!B:C,2,0) -> #N/A
A68: 2022 | B68: 7 | C68: 29 | D68: FW22 | E68: NECKLACE | F68: FW22 | G68: 1759667 | H68: 1534000 | I68: 44754 | J68: 174880 | K68: RHN580 | L68: GEODE | M68: RHN | N68: WACC | O68: 580 | P68: 1 | Q68: Split | R68: 7699500 | S68: 7129167 | T68: 10 | U68: 792130 | V68: 855500 | W68: Ngoc_Nguyen | X68: GEO - NECKLACE AGATE | Y68: Ms. To Thi Hanh | Z68: E8 | AA68: 18 | AB68: CREAM | AC68: 8555000 | AD68: UN | AE68: 7921296 | AF68: KIEUDIEM_NGUYENHN | AG68: 0916671961 | AH68: 5369500 | AI68: =VLOOKUP(Sales[[#This Row],[Store]],'Store lay bao cao'!A:B,2,0) -> Lấy BC | AJ68: =VLOOKUP(Sales[[#This Row],[Associate]],'Associate Status'!B:C,2,0) -> Retired
A69: 2022 | B69: 7 | C69: 29 | D69: FW22 | E69: NECKLACE | F69: FW22 | G69: 2801931 | H69: 2442600 | I69: 44754 | J69: 174896 | K69: RHN580 | L69: GEODE | M69: RHN | N69: WACC | O69: 580 | P69: 1 | Q69: Split | R69: 12213000 | S69: 11308333 | T69: 10 | U69: 1256481 | V69: 1357000 | W69: Ngoc_Nguyen | X69: GEO - NECKLACE PEARL | Y69: Ms. To Thi Hanh | Z69: I2 | AA69: 18 | AB69: WHITE | AC69: 13570000 | AD69: UN | AE69: 12564815 | AF69: KIEUDIEM_NGUYENHN | AG69: 0916671961 | AH69: 8506402 | AI69: =VLOOKUP(Sales[[#This Row],[Store]],'Store lay bao cao'!A:B,2,0) -> Lấy BC | AJ69: =VLOOKUP(Sales[[#This Row],[Associate]],'Associate Status'!B:C,2,0) -> Retired
A70: 2022 | B70: 7 | C70: 29 | D70: FW22 | E70: NECKLACE | F70: FW22 | G70: 1641228 | H70: 1430750 | I70: 44754 | J70: 174888 | K70: RHN580 | L70: GEODE | M70: RHN | N70: WACC | O70: 580 | P70: 1 | Q70: Split | R70: 7168500 | S70: 6637500 | T70: 10 | U70: 737500 | V70: 796500 | W70: Ngoc_Nguyen | X70: GEO - NECKLACE BLACK AGATE | Y70: Ms. To Thi Hanh | Z70: E4 | AA70: 18 | AB70: BLACK | AC70: 7965000 | AD70: UN | AE70: 7375000 | AF70: KIEUDIEM_NGUYENHN | AG70: 0916671961 | AH70: 4996272 | AI70: =VLOOKUP(Sales[[#This Row],[Store]],'Store lay bao cao'!A:B,2,0) -> Lấy BC | AJ70: =VLOOKUP(Sales[[#This Row],[Associate]],'Associate Status'!B:C,2,0) -> Retired
A71: 2022 | B71: 7 | C71: 29 | D71: FW22 | E71: NECKLACE | F71: FW22 | G71: 2368783 | H71: 2065000 | I71: 44754 | J71: 174902 | K71: RHN580 | L71: GEODE | M71: RHN | N71: WACC | O71: 580 | P71: 1 | Q71: Split | R71: 10354500 | S71: 9587500 | T71: 10 | U71: 1065278 | V71: 1150500 | W71: Ngoc_Nguyen | X71: GEO - NECKLACE AMBER | Y71: Ms. To Thi Hanh | Z71: G8 | AA71: 18 | AB71: GOLD/BROWN | AC71: 11505000 | AD71: UN | AE71: 10652778 | AF71: KIEUDIEM_NGUYENHN | AG71: 0916671961 | AH71: 7218717 | AI71: =VLOOKUP(Sales[[#This Row],[Store]],'Store lay bao cao'!A:B,2,0) -> Lấy BC | AJ71: =VLOOKUP(Sales[[#This Row],[Associate]],'Associate Status'!B:C,2,0) -> Retired
A72: 2022 | B72: 7 | C72: 29 | D72: FW22 | E72: NECKLACE | F72: FW22 | G72: 4263807 | H72: 3717000 | I72: 44754 | J72: 174859 | K72: RHN580 | L72: GEODE | M72: RHN | N72: WACC | O72: 580 | P72: 1 | Q72: Split | R72: 21240000 | S72: 19666667 | T72: 10 | U72: 2185185 | V72: 2360000 | W72: Ngoc_Nguyen | X72: GEO - NECKLACE PEARL | Y72: Ms. To Thi Hanh | Z72: A60 | AA72: 18 | AB72: WHITE | AC72: 23600000 | AD72: UN | AE72: 21851852 | AF72: CHINH_NGUYEN | AG72: 0916671961 | AH72: 15402860 | AI72: =VLOOKUP(Sales[[#This Row],[Store]],'Store lay bao cao'!A:B,2,0) -> Lấy BC | AJ72: =VLOOKUP(Sales[[#This Row],[Associate]],'Associate Status'!B:C,2,0) -> Active
A73: 2022 | B73: 7 | C73: 29 | D73: FW22 | E73: NECKLACE | F73: FW22 | G73: 2554901 | H73: 2227250 | I73: 44756 | J73: 174898 | K73: RHN588 | L73: GEODE | M73: RHN | N73: WACC | O73: 588 | P73: 1 | Q73: Check | R73: 12390000 | S73: 11472222 | T73: 0 | U73: 0 | V73: 0 | W73: Ha_Nguyen | X73: GEO - NECKLACE TOURMALINE | Y73: Ms. Nguyen Hong Thuy | Z73: H4 | AA73: 17 | AB73: MUTI | AC73: 12390000 | AD73: UN | AE73: 11472222 | AF73: SON_NGUYENVAN_SALE | AG73: 0988660486 | AH73: 8917321 | AI73: =VLOOKUP(Sales[[#This Row],[Store]],'Store lay bao cao'!A:B,2,0) -> Lấy BC | AJ73: =VLOOKUP(Sales[[#This Row],[Associate]],'Associate Status'!B:C,2,0) -> #N/A
A74: 2022 | B74: 7 | C74: 30 | D74: FW22 | E74: NECKLACE | F74: FW22 | G74: 1759667 | H74: 1534000 | I74: 44765 | J74: 174878 | K74: RHN644 | L74: GEODE | M74: RHN | N74: WACC | O74: 644 | P74: 1 | Q74: Split | R74: 7699500 | S74: 7129167 | T74: 10 | U74: 792130 | V74: 855500 | W74: Huyen_Dang | X74: GEO - NECKLACE LAPIS | Y74: Mrs. Nguyen Thi Linh San | Z74: E8 | AA74: 15 | AB74: LAPIS | AC74: 8555000 | AD74: UN | AE74: 7921296 | AF74: CHINH_NGUYEN | AG74: 0982246268 | AH74: 5369500 | AI74: =VLOOKUP(Sales[[#This Row],[Store]],'Store lay bao cao'!A:B,2,0) -> Lấy BC | AJ74: =VLOOKUP(Sales[[#This Row],[Associate]],'Associate Status'!B:C,2,0) -> Active
A75: 2022 | B75: 7 | C75: 30 | D75: FW22 | E75: NECKLACE | F75: FW22 | G75: 1279142 | H75: 1115100 | I75: 44765 | J75: 174867 | K75: RHN644 | L75: GEODE | M75: RHN | N75: WACC | O75: 644 | P75: 1 | Q75: Split | R75: 5575500 | S75: 5162500 | T75: 10 | U75: 573611 | V75: 619500 | W75: Huyen_Dang | X75: GEO - NECKLACE MOSS AGATE | Y75: Mrs. Nguyen Thi Linh San | Z75: D2 | AA75: 15 | AB75: GREEN | AC75: 6195000 | AD75: UN | AE75: 5736111 | AF75: HOA_TRAN | AG75: 0982246268 | AH75: 3883358 | AI75: =VLOOKUP(Sales[[#This Row],[Store]],'Store lay bao cao'!A:B,2,0) -> Lấy BC | AJ75: =VLOOKUP(Sales[[#This Row],[Associate]],'Associate Status'!B:C,2,0) -> Retired
A76: 2022 | B76: 7 | C76: 30 | D76: FW22 | E76: EARRINGS | F76: FW22 | G76: 791850 | H76: 690300 | I76: 44766 | J76: 174907 | K76: RHN650 | L76: GEODE | M76: RHN | N76: WACC | O76: 650 | P76: 1 | Q76: Credit Card | R76: 3451500 | S76: 3195833 | T76: 10 | U76: 355093 | V76: 383500 | W76: Huyen_Dang | X76: GEO - EARRING CORNELIAN | Y76: Ms. Nguyen thu Cuc | Z76: B6 | AA76: 18 | AB76: RED | AC76: 3835000 | AD76: UN | AE76: 3550926 | AF76: NGHIA_NGUYENHN | AG76: 0913022326 | AH76: 2403983 | AI76: =VLOOKUP(Sales[[#This Row],[Store]],'Store lay bao cao'!A:B,2,0) -> Lấy BC | AJ76: =VLOOKUP(Sales[[#This Row],[Associate]],'Associate Status'!B:C,2,0) -> #N/A
A77: 2022 | B77: 7 | C77: 30 | D77: FW22 | E77: NECKLACE | F77: FW22 | G77: 1759667 | H77: 1534000 | I77: 44766 | J77: 174887 | K77: RHN650 | L77: GEODE | M77: RHN | N77: WACC | O77: 650 | P77: 1 | Q77: Credit Card | R77: 7699500 | S77: 7129167 | T77: 10 | U77: 792130 | V77: 855500 | W77: Huyen_Dang | X77: GEO - NECKLACE CORNELIAN | Y77: Ms. Nguyen thu Cuc | Z77: E8 | AA77: 18 | AB77: RED/GOLD | AC77: 8555000 | AD77: UN | AE77: 7921296 | AF77: NGHIA_NGUYENHN | AG77: 0913022326 | AH77: 5369500 | AI77: =VLOOKUP(Sales[[#This Row],[Store]],'Store lay bao cao'!A:B,2,0) -> Lấy BC | AJ77: =VLOOKUP(Sales[[#This Row],[Associate]],'Associate Status'!B:C,2,0) -> #N/A
... A83: 2022 | B83: 8 | C83: 34 | D83: FW22 | E83: NECKLACE | F83: FW22 | G83: 1583701 | H83: 1380600 | I83: 44790 | J83: 174886 | K83: RWR5691 | L83: GEODE | M83: RWR | N83: WACC | O83: 5691 | P83: 1 | Q83: Credit Card | R83: 6903000 | S83: 6391667 | T83: 10 | U83: 710185 | V83: 767000 | W83: Nghia_Nguyen | X83: GEO - NECKLACE MOSS AGATE | Y83: Mrs. Nguyen Thi Thao Nhi | Z83: E2 | AA83: 15 | AB83: GREEN | AC83: 7670000 | AD83: UN | AE83: 7101852 | AF83: HUONG_NGUYENKIM | AG83: 0908297658 | AH83: 4807966 | AI83: =VLOOKUP(Sales[[#This Row],[Store]],'Store lay bao cao'!A:B,2,0) -> Lấy BC | AJ83: =VLOOKUP(Sales[[#This Row],[Associate]],'Associate Status'!B:C,2,0) -> Active
A84: 2022 | B84: 8 | C84: 35 | D84: SS13 | E84: JEWELRY | F84: SS13 | G84: 11262801 | H84: 11262801 | I84: 44798 | J84: 52829 | K84: RWR5761 | L84: ROSA MARIA | M84: RWR | N84: WACC | O84: 5761 | P84: 1 | Q84: Credit Card | R84: 33785100 | S84: 31282500 | T84: 10 | U84: 3475833 | V84: 3753900 | W84: Nghia_Nguyen | X84: RM Silver ring-top silver treated frame set with icy grey diamonds-middle silver concave(mat) | Y84: Mrs. Duong Quynh Huong | Z84: BEGUM(TB) S-ST-S DIX (ICY GRIS) | AA84: 13 | AB84: SILVER/GREY | AC84: 37539000 | AD84: 10 | AE84: 34758333 | AF84: LINH_LUU | AG84: 0937369369 | AH84: 20019699 | AI84: =VLOOKUP(Sales[[#This Row],[Store]],'Store lay bao cao'!A:B,2,0) -> Lấy BC | AJ84: =VLOOKUP(Sales[[#This Row],[Associate]],'Associate Status'!B:C,2,0) -> Active
A85: 2022 | B85: 8 | C85: 35 | D85: FW22 | E85: NECKLACE | F85: FW22 | G85: 3654692 | H85: 3186000 | I85: 44801 | J85: 174856 | K85: RWR5778 | L85: GEODE | M85: RWR | N85: WACC | O85: 5778 | P85: 1 | Q85: Split | R85: 20650000 | S85: 19120370 | T85: 0 | U85: 0 | V85: 0 | W85: Nghia_Nguyen | X85: GEO - NECKLACE AMETHIST | Y85: Mr. Le Thanh Hung | Z85: A40 | AA85: 10 | AB85: MIX ROSE | AC85: 20650000 | AD85: UN | AE85: 19120370 | AF85: MAI_NGUYEN | AG85: 0986166668 | AH85: 15465678 | AI85: =VLOOKUP(Sales[[#This Row],[Store]],'Store lay bao cao'!A:B,2,0) -> Lấy BC | AJ85: =VLOOKUP(Sales[[#This Row],[Associate]],'Associate Status'!B:C,2,0) -> Retired
A86: 2022 | B86: 9 | C86: 37 | D86: FW22 | E86: NECKLACE | F86: FW22 | G86: 2064225 | H86: 1799500 | I86: 44815 | J86: 174893 | K86: RWR5837 | L86: GEODE | M86: RWR | N86: WACC | O86: 5837 | P86: 1 | Q86: Credit Card | R86: 10030000 | S86: 9287037 | T86: 0 | U86: 0 | V86: 0 | W86: Nghia_Nguyen | X86: GEO - NECKLACE PEARL | Y86: Ms. Hong Pham | Z86: F8, | AA86: 16 | AB86: WHITE. | AC86: 10030000 | AD86: UN | AE86: 9287037 | AF86: HUONG_NGUYENKIM | AG86: 0945555129 | AH86: 7222812 | AI86: =VLOOKUP(Sales[[#This Row],[Store]],'Store lay bao cao'!A:B,2,0) -> Lấy BC | AJ86: =VLOOKUP(Sales[[#This Row],[Associate]],'Associate Status'!B:C,2,0) -> Active
A87: 2022 | B87: 9 | C87: 37 | D87: FW22 | E87: NECKLACE | F87: FW22 | G87: 1461877 | H87: 1274400 | I87: 44815 | J87: 174872 | K87: RWR5837 | L87: GEODE | M87: RWR | N87: WACC | O87: 5837 | P87: 1 | Q87: Credit Card | R87: 7080000 | S87: 6555556 | T87: 0 | U87: 0 | V87: 0 | W87: Nghia_Nguyen | X87: GEO - NECKLACE MOKAITE | Y87: Ms. Hong Pham | Z87: D8 | AA87: 16 | AB87: MUTI | AC87: 7080000 | AD87: UN | AE87: 6555556 | AF87: HUONG_NGUYENKIM | AG87: 0945555129 | AH87: 5093679 | AI87: =VLOOKUP(Sales[[#This Row],[Store]],'Store lay bao cao'!A:B,2,0) -> Lấy BC | AJ87: =VLOOKUP(Sales[[#This Row],[Associate]],'Associate Status'!B:C,2,0) -> Active
A88: 2022 | B88: 9 | C88: 37 | D88: FW22 | E88: NECKLACE | F88: FW22 | G88: 1759667 | H88: 1534000 | I88: 44815 | J88: 174885 | K88: RWR5837 | L88: GEODE | M88: RWR | N88: WACC | O88: 5837 | P88: 1 | Q88: Credit Card | R88: 8555000 | S88: 7921296 | T88: 0 | U88: 0 | V88: 0 | W88: Nghia_Nguyen | X88: GEO - NECKLACE MOSS AGATE | Y88: Ms. Hong Pham | Z88: E8. | AA88: 16 | AB88: GREEN | AC88: 8555000 | AD88: UN | AE88: 7921296 | AF88: HUONG_NGUYENKIM | AG88: 0945555129 | AH88: 6161629 | AI88: =VLOOKUP(Sales[[#This Row],[Store]],'Store lay bao cao'!A:B,2,0) -> Lấy BC | AJ88: =VLOOKUP(Sales[[#This Row],[Associate]],'Associate Status'!B:C,2,0) -> Active
A89: 2022 | B89: 9 | C89: 40 | D89: FW22 | E89: NECKLACE | F89: FW22 | G89: 4568365 | H89: 3982500 | I89: 44831 | J89: 174860 | K89: RWR5883 | L89: GEODE | M89: RWR | N89: WACC | O89: 5883 | P89: 1 | Q89: Credit Card | R89: 22567500 | S89: 20895833 | T89: 10 | U89: 2321759 | V89: 2507500 | W89: Ha_Nguyen | X89: GEO - NECKLACE PEARL | Y89: Ms. Nguyen Thi Thu Hong | Z89: A70 | AA89: 16 | AB89: WHITE | AC89: 25075000 | AD89: UN | AE89: 23217593 | AF89: DUNG_TRAN | AG89: 0937009009 | AH89: 16327468 | AI89: =VLOOKUP(Sales[[#This Row],[Store]],'Store lay bao cao'!A:B,2,0) -> Lấy BC | AJ89: =VLOOKUP(Sales[[#This Row],[Associate]],'Associate Status'!B:C,2,0) -> Active
A90: 2022 | B90: 9 | C90: 40 | D90: FW22 | E90: EARRINGS | F90: FW22 | G90: 609116 | H90: 531000 | I90: 44834 | J90: 174908 | K90: RWR5895 | L90: GEODE | M90: RWR | N90: WACC | O90: 5895 | P90: 1 | Q90: Credit Card | R90: 2802500 | S90: 2594907 | T90: 5 | U90: 136574 | V90: 147500 | W90: Ha_Nguyen | X90: GEO - EARRING CORNELIAN | Y90: Ms. Tran Lam Thai | Z90: B0 | AA90: 20 | AB90: RED | AC90: 2950000 | AD90: UN | AE90: 2731481 | AF90: TRANG_TRAN | AG90: 0907502222 | AH90: 1985791 | AI90: =VLOOKUP(Sales[[#This Row],[Store]],'Store lay bao cao'!A:B,2,0) -> Lấy BC | AJ90: =VLOOKUP(Sales[[#This Row],[Associate]],'Associate Status'!B:C,2,0) -> Retired
A91: 2022 | B91: 10 | C91: 43 | D91: FW22 | E91: NECKLACE | F91: FW22 | G91: 1759667 | H91: 1534000 | I91: 44854 | J91: 174882 | K91: RHN1156 | L91: GEODE | M91: RHN | N91: WACC | O91: 1156 | P91: 1 | Q91: Credit Card | R91: 8555000 | S91: 7921296 | T91: 0 | U91: 0 | V91: 0 | W91: Ngoc_Nguyen | X91: GEO - NECKLACE MADREPORE | Y91: Le Ngoc Lien | Z91: E8 | AA91: 15 | AB91: Red/black | AC91: 8555000 | AD91: UN | AE91: 7921296 | AF91: HOA_TRAN | AG91: 0916596868 | AH91: 6161629 | AI91: =VLOOKUP(Sales[[#This Row],[Store]],'Store lay bao cao'!A:B,2,0) -> Lấy BC | AJ91: =VLOOKUP(Sales[[#This Row],[Associate]],'Associate Status'!B:C,2,0) -> Retired
A92: 2022 | B92: 11 | C92: 45 | D92: FW22 | E92: EARRINGS | F92: FW22 | G92: 791850 | H92: 690300 | I92: 44867 | J92: 174905 | K92: RHN1210 | L92: GEODE | M92: RHN | N92: WACC | O92: 1210 | P92: 1 | Q92: Check | R92: 3835000 | S92: 3550926 | T92: 0 | U92: 0 | V92: 0 | W92: Ngoc_Nguyen | X92: GEO - EARRING M.PEARL | Y92: Ms. Do Thi Kim Lien | Z92: B6 | AA92: 16 | AB92: WHITE | AC92: 3835000 | AD92: UN | AE92: 3550926 | AF92: HUE_BUI | AG92: 0936383838 | AH92: 2759076 | AI92: =VLOOKUP(Sales[[#This Row],[Store]],'Store lay bao cao'!A:B,2,0) -> Lấy BC | AJ92: =VLOOKUP(Sales[[#This Row],[Associate]],'Associate Status'!B:C,2,0) -> Active
A93: 2022 | B93: 11 | C93: 48 | D93: FW22 | E93: NECKLACE | F93: FW22 | G93: 1759667 | H93: 1534000 | I93: 44886 | J93: 174881 | K93: RWR6069 | L93: GEODE | M93: RWR | N93: WACC | O93: 6069 | P93: 1 | Q93: Credit Card | R93: 8555000 | S93: 7921296 | T93: 0 | U93: 0 | V93: 0 | W93: Ha_Nguyen | X93: GEO - NECKLACE MADREPORE | Y93: Tourist | Z93: E8 | AA93: 19 | AB93: RED | AC93: 8555000 | AD93: UN | AE93: 7921296 | AF93: DUNG_TRAN | AH93: 6161629 | AI93: =VLOOKUP(Sales[[#This Row],[Store]],'Store lay bao cao'!A:B,2,0) -> Lấy BC | AJ93: =VLOOKUP(Sales[[#This Row],[Associate]],'Associate Status'!B:C,2,0) -> Active
A94: 2022 | B94: 11 | C94: 48 | D94: FW22 | E94: NECKLACE | F94: FW22 | G94: 5143641 | H94: 4484000 | I94: 44890 | J94: 174857 | K94: RHN1316 | L94: GEODE | M94: RHN | N94: WACC | O94: 1316 | P94: 1 | Q94: Credit Card | R94: 25089750 | S94: 23231250 | T94: 10 | U94: 2581250 | V94: 2787750 | W94: Ngoc_Nguyen | X94: GEO - NECKLACE PEARL | Y94: Mrs. Le Thi Hoa | Z94: A8P | AA94: 12 | AB94: YELLOW | AC94: 27877500 | AD94: UN | AE94: 25812500 | AF94: NGHIA_NGUYENHN | AG94: 0913221545 | AH94: 18087609 | AI94: =VLOOKUP(Sales[[#This Row],[Store]],'Store lay bao cao'!A:B,2,0) -> Lấy BC | AJ94: =VLOOKUP(Sales[[#This Row],[Associate]],'Associate Status'!B:C,2,0) -> #N/A
A95: 2022 | B95: 11 | C95: 48 | D95: SS12 | E95: JEWELRY | F95: SS12 | G95: 4197600 | H95: 4197600 | I95: 44890 | J95: 37092 | K95: RHN1330 | L95: ROSA MARIA | M95: RHN | N95: WACC | O95: 1330 | P95: 1 | Q95: Check | R95: 15700000 | S95: 14537037 | T95: 0 | U95: 0 | V95: 0 | W95: Ngoc_Nguyen | X95: RM Silver ring-top oval | Y95: Le Hoang Phuong | Z95: BALSAM R (TB) | AA95: 15 | AB95: SILVER | AC95: 15700000 | AD95: 11 | AE95: 14537037 | AF95: CHINH_NGUYEN | AG95: 0388883333 | AH95: 10339437 | AI95: =VLOOKUP(Sales[[#This Row],[Store]],'Store lay bao cao'!A:B,2,0) -> Lấy BC | AJ95: =VLOOKUP(Sales[[#This Row],[Associate]],'Associate Status'!B:C,2,0) -> Active
A96: 2022 | B96: 12 | C96: 51 | D96: SS23 | E96: EARRINGS | F96: SS23 | G96: 95851538 | H96: 110880000 | I96: 44912 | J96: 180390 | K96: RWR6209 | L96: ARTUR SCHOLL | M96: RWR | N96: WACC | O96: 6209 | P96: 1 | Q96: Split | R96: 218500000 | S96: 202314815 | T96: 5 | U96: 10648148 | V96: 11500000 | W96: Ha_Nguyen | X96: ATS - PG Pr. of Earrings: brown | Y96: Mrs. Duong Quynh Huong | Z96: 30/15127R/CH | AA96: 15 | AB96: BROWN DIA | AC96: 230000000 | AD96: O/S | AE96: 212962963 | AF96: LINH_LUU | AG96: 0937369369 | AH96: 106463277 | AI96: =VLOOKUP(Sales[[#This Row],[Store]],'Store lay bao cao'!A:B,2,0) -> Lấy BC | AJ96: =VLOOKUP(Sales[[#This Row],[Associate]],'Associate Status'!B:C,2,0) -> Active
A97: 2022 | B97: 12 | C97: 51 | D97: FW22 | E97: NECKLACE | F97: FW22 | G97: 1336670 | H97: 1165250 | I97: 44912 | J97: 174874 | K97: RWT2296 | L97: GEODE | M97: RWT | N97: WACC | O97: 2296 | P97: 1 | Q97: Credit Card | R97: 6490000 | S97: 6009259 | T97: 0 | U97: 0 | V97: 0 | W97: Chau_Vuong | X97: GEO - NECKLACE TORMALINE | Y97: Ms. Le Thi Thanh Mai | Z97: D4 | AA97: 10 | AB97: MUTI | AC97: 6490000 | AD97: UN | AE97: 6009259 | AF97: HUYNH_NGUYEN | AG97: 0933530066 | AH97: 4672589 | AI97: =VLOOKUP(Sales[[#This Row],[Store]],'Store lay bao cao'!A:B,2,0) -> Lấy BC | AJ97: =VLOOKUP(Sales[[#This Row],[Associate]],'Associate Status'!B:C,2,0) -> Retired
A98: 2022 | B98: 12 | C98: 51 | D98: FW22 | E98: NECKLACE | F98: FW22 | G98: 1218231 | H98: 1062000 | I98: 44912 | J98: 174873 | K98: RWT2296 | L98: GEODE | M98: RWT | N98: WACC | O98: 2296 | P98: 1 | Q98: Credit Card | R98: 5900000 | S98: 5462963 | T98: 0 | U98: 0 | V98: 0 | W98: Chau_Vuong | X98: GEO - NECKLACE CAT'S EYE | Y98: Ms. Le Thi Thanh Mai | Z98: D0 | AA98: 10 | AB98: YELLOW | AC98: 5900000 | AD98: UN | AE98: 5462963 | AF98: HUYNH_NGUYEN | AG98: 0933530066 | AH98: 4244732 | AI98: =VLOOKUP(Sales[[#This Row],[Store]],'Store lay bao cao'!A:B,2,0) -> Lấy BC | AJ98: =VLOOKUP(Sales[[#This Row],[Associate]],'Associate Status'!B:C,2,0) -> Retired
A99: 2022 | B99: 12 | C99: 51 | D99: FW22 | E99: NECKLACE | F99: FW22 | G99: 1150552 | H99: 1003000 | I99: 44913 | J99: 174864 | K99: RWT2303 | L99: GEODE | M99: RWT | N99: WACC | O99: 2303 | P99: 1 | Q99: Credit Card | R99: 5605000 | S99: 5189815 | T99: 0 | U99: 0 | V99: 0 | W99: Chau_Vuong | X99: GEO - NECKLACE MOSS AGATE | Y99: Mrs. Thai Cam Linh | Z99: C8 | AA99: 11 | AB99: GREEN | AC99: 5605000 | AD99: UN | AE99: 5189815 | AF99: HUYNH_NGUYEN | AG99: 0917568851 | AH99: 4039263 | AI99: =VLOOKUP(Sales[[#This Row],[Store]],'Store lay bao cao'!A:B,2,0) -> Lấy BC | AJ99: =VLOOKUP(Sales[[#This Row],[Associate]],'Associate Status'!B:C,2,0) -> Retired
A100: 2022 | B100: 12 | C100: 52 | D100: SS23 | E100: RING | F100: SS23 | G100: 71305867 | H100: 82600000 | I100: 44915 | J100: 180402 | K100: RWR6222 | L100: ARTUR SCHOLL | M100: RWR | N100: WACC | O100: 6222 | P100: 1 | Q100: Check | R100: 165000600 | S100: 152778333 | T100: 8.33 | U100: 13888333 | V100: 14999400 | W100: Nghia_Nguyen | X100: ATS - WG Ring: dia 0,33ct G/VS + green tourmaline 5,90ct + ruby 1,87ct | Y100: Mrs. Dinh Thanh Huong | Z100: 93/14294W/TR | AA100: 16 | AB100: DIA + GREEN + PI | AC100: 180000000 | AD100: O/S | AE100: 166666667 | AF100: NGHIA_NGUYEN | AG100: 0903256655 | AH100: 81472466 | AI100: =VLOOKUP(Sales[[#This Row],[Store]],'Store lay bao cao'!A:B,2,0) -> Lấy BC | AJ100: =VLOOKUP(Sales[[#This Row],[Associate]],'Associate Status'!B:C,2,0) -> Active
A101: 2022 | B101: 12 | C101: 52 | D101: SS23 | E101: EARRINGS | F101: SS23 | G101: 118696024 | H101: 137200000 | I101: 44915 | J101: 180400 | K101: RWR6221 | L101: ARTUR SCHOLL | M101: RWR | N101: WACC | O101: 6221 | P101: 1 | Q101: Account | R101: 285000000 | S101: 263888889 | T101: 5 | U101: 13888889 | V101: 15000000 | W101: Nghia_Nguyen | X101: ATS - PG Pr. of Earrings: pink tourmaline 11,95ct + green tourmaline 16,15ct + green sapphire 1,08ct | Y101: Mrs. Phan Lan Phuong | Z101: 88/01660R/T | AA101: 10 | AB101: PINK + GREEN | AC101: 300000000 | AD101: O/S | AE101: 277777778 | AF101: NGHIA_NGUYEN | AG101: 0977317777 | AH101: 145192865 | AI101: =VLOOKUP(Sales[[#This Row],[Store]],'Store lay bao cao'!A:B,2,0) -> Lấy BC | AJ101: =VLOOKUP(Sales[[#This Row],[Associate]],'Associate Status'!B:C,2,0) -> Active
A102: 2022 | B102: 12 | C102: 52 | D102: SS23 | E102: EARRINGS | F102: SS23 | G102: 34851900 | H102: 40600000 | I102: 44916 | J102: 180403 | K102: RWR6230 | L102: ARTUR SCHOLL | M102: RWR | N102: WACC | O102: 6230 | P102: 1 | Q102: Credit Card | R102: 108004000 | S102: 100003704 | T102: 16.92 | U102: 20366667 | V102: 21996000 | W102: Nghia_Nguyen | X102: ATS - PG Pr. of Earrings: dia 0,57ct G/VS + amethyst 25,76ct | Y102: Mrs. Dinh Thanh Huong | Z102: 93/14408R/AM | AA102: 14 | AB102: DIA + AMETHYST + | AC102: 130000000 | AD102: O/S | AE102: 120370370 | AF102: VUONG_VO | AG102: 0903256655 | AH102: 65151804 | AI102: =VLOOKUP(Sales[[#This Row],[Store]],'Store lay bao cao'!A:B,2,0) -> Lấy BC | AJ102: =VLOOKUP(Sales[[#This Row],[Associate]],'Associate Status'!B:C,2,0) -> Active
A103: 2022 | B103: 12 | C103: 53 | D103: SS23 | E103: RING | F103: SS23 | G103: 48218354 | H103: 56000000 | I103: 44922 | J103: 180391 | K103: RHN1515 | L103: ARTUR SCHOLL | M103: RHN | N103: WACC | O103: 1515 | P103: 1 | Q103: Cash | R103: 130000000 | S103: 120370370 | T103: 0 | U103: 0 | V103: 0 | W103: Ngoc_Nguyen | X103: ATS - PG Ring: dia 1,42ct G/VS + rubiy 0,50ct + pink sapphire 2,07ct | Y103: Pham Thanh Huong | Z103: 30/17372R/PS | AA103: 10 | AB103: RUBY + PINK SAPP | AC103: 130000000 | AD103: O/S | AE103: 120370370 | AF103: NGHIA_NGUYENHN | AG103: 0934449329 | AH103: 72152016 | AI103: =VLOOKUP(Sales[[#This Row],[Store]],'Store lay bao cao'!A:B,2,0) -> Lấy BC | AJ103: =VLOOKUP(Sales[[#This Row],[Associate]],'Associate Status'!B:C,2,0) -> #N/A
A104: 2022 | B104: 12 | C104: 53 | D104: SS23 | E104: EARRINGS | F104: SS23 | G104: 32907688 | H104: 38360000 | I104: 44922 | J104: 180393 | K104: RHN1515 | L104: ARTUR SCHOLL | M104: RHN | N104: WACC | O104: 1515 | P104: 1 | Q104: Cash | R104: 120000000 | S104: 111111111 | T104: 0 | U104: 0 | V104: 0 | W104: Ngoc_Nguyen | X104: ATS - WG Pr. of Earrings: dia 0,13ct G/VS + brown dia 0,32ct + tsavorite 0,44ct | Y104: Pham Thanh Huong | Z104: 30/AW12442/TS | AA104: 10 | AB104: BROWN DIA + TSAV | AC104: 120000000 | AD104: O/S | AE104: 111111111 | AF104: NGHIA_NGUYENHN | AG104: 0934449329 | AH104: 78203423 | AI104: =VLOOKUP(Sales[[#This Row],[Store]],'Store lay bao cao'!A:B,2,0) -> Lấy BC | AJ104: =VLOOKUP(Sales[[#This Row],[Associate]],'Associate Status'!B:C,2,0) -> #N/A
A105: 2022 | B105: 12 | C105: 53 | D105: SS23 | E105: EARRINGS | F105: SS23 | G105: 17205506 | H105: 20272000 | I105: 44922 | J105: 180405 | K105: RHN1515 | L105: ARTUR SCHOLL | M105: RHN | N105: WACC | O105: 1515 | P105: 1 | Q105: Cash | R105: 70000000 | S105: 64814815 | T105: 0 | U105: 0 | V105: 0 | W105: Ngoc_Nguyen | X105: ATS - PG Pr. of Earrings: amethyst 1,82ct + blue topaze 1,43ct + citrine 0,39ct + green amethyst 6,05ct | Y105: Pham Thanh Huong | Z105: 93/14899R/GAM | AA105: 10 | AB105: AMETHYST + BLUE | AC105: 70000000 | AD105: O/S | AE105: 64814815 | AF105: NGHIA_NGUYENHN | AG105: 0934449329 | AH105: 47609309 | AI105: =VLOOKUP(Sales[[#This Row],[Store]],'Store lay bao cao'!A:B,2,0) -> Lấy BC | AJ105: =VLOOKUP(Sales[[#This Row],[Associate]],'Associate Status'!B:C,2,0) -> #N/A
...

Sheet Inventory TY
A1: Year | B1: Month | C1: Date | D1: Item # | E1: Vendor Name | F1: Dept Name | G1: Season | H1: Categories | I1: Landed Cost | J1: Store | K1: Inventory Qty | L1: TT Landed Cost
A2: 2026 | B2: 1 | C2: 46034 | D2: 30044 | E2: ROSA MARIA | F2: WACC | G2: FW11 | H2: JEWELRY | I2: 3698446 | J2: RWR | K2: 1 | L2: =InventoryTY[[#This Row],[Landed Cost]]*InventoryTY[[#This Row],[Inventory Qty]] -> 3698446
A3: 2026 | B3: 1 | C3: 46034 | D3: 90573 | E3: ROSA MARIA | F3: WACC | G3: FW16 | H3: JEWELRY | I3: 9475200 | J3: RHN | K3: 1 | L3: =InventoryTY[[#This Row],[Landed Cost]]*InventoryTY[[#This Row],[Inventory Qty]] -> 9475200
A4: 2026 | B4: 1 | C4: 46034 | D4: 90583 | E4: ROSA MARIA | F4: WACC | G4: FW16 | H4: JEWELRY | I4: 1945800 | J4: RWR | K4: 1 | L4: =InventoryTY[[#This Row],[Landed Cost]]*InventoryTY[[#This Row],[Inventory Qty]] -> 1945800
A5: 2026 | B5: 1 | C5: 46034 | D5: 117902 | E5: ROSA MARIA | F5: WACC | G5: FW17 | H5: JEWELRY | I5: 34545000 | J5: RWR | K5: 1 | L5: =InventoryTY[[#This Row],[Landed Cost]]*InventoryTY[[#This Row],[Inventory Qty]] -> 34545000
A6: 2026 | B6: 1 | C6: 46034 | D6: 132032 | E6: Rosa Maria | F6: WACC | G6: SS19 | H6: NECKLACE | I6: 5306700 | J6: RHN | K6: 1 | L6: =InventoryTY[[#This Row],[Landed Cost]]*InventoryTY[[#This Row],[Inventory Qty]] -> 5306700
A7: 2026 | B7: 1 | C7: 46034 | D7: 133939 | E7: Ted Muehling | F7: WACC | G7: SS19 | H7: PIN | I7: 17358250 | J7: RHN | K7: 1 | L7: =InventoryTY[[#This Row],[Landed Cost]]*InventoryTY[[#This Row],[Inventory Qty]] -> 17358250
A8: 2026 | B8: 1 | C8: 46034 | D8: 139754 | E8: Ted Muehling | F8: WACC | G8: SS19 | H8: BROOCH | I8: 10682000 | J8: RHN | K8: 1 | L8: =InventoryTY[[#This Row],[Landed Cost]]*InventoryTY[[#This Row],[Inventory Qty]] -> 10682000
A9: 2026 | B9: 1 | C9: 46034 | D9: 151866 | E9: ROSA MARIA | F9: WACC | G9: SS20 | H9: RING | I9: 3281775 | J9: RHN | K9: 1 | L9: =InventoryTY[[#This Row],[Landed Cost]]*InventoryTY[[#This Row],[Inventory Qty]] -> 3281775
A10: 2026 | B10: 1 | C10: 46034 | D10: 151877 | E10: ROSA MARIA | F10: WACC | G10: SS20 | H10: RING | I10: 14802900 | J10: RHN | K10: 1 | L10: =InventoryTY[[#This Row],[Landed Cost]]*InventoryTY[[#This Row],[Inventory Qty]] -> 14802900
A11: 2026 | B11: 1 | C11: 46034 | D11: 170999 | E11: CONFUORTO GIOIELLY ITALY | F11: WACC | G11: SS22 | H11: EARRINGS | I11: 1622500 | J11: RWT | K11: 3 | L11: =InventoryTY[[#This Row],[Landed Cost]]*InventoryTY[[#This Row],[Inventory Qty]] -> 4867500
A12: 2026 | B12: 1 | C12: 46034 | D12: 171001 | E12: CONFUORTO GIOIELLY ITALY | F12: WACC | G12: SS22 | H12: EARRINGS | I12: 1062000 | J12: RWD | K12: 1 | L12: =InventoryTY[[#This Row],[Landed Cost]]*InventoryTY[[#This Row],[Inventory Qty]] -> 1062000
A13: 2026 | B13: 1 | C13: 46034 | D13: 171015 | E13: GEODE | F13: WACC | G13: SS22 | H13: NECKLACE | I13: 2537000 | J13: RWR | K13: 1 | L13: =InventoryTY[[#This Row],[Landed Cost]]*InventoryTY[[#This Row],[Inventory Qty]] -> 2537000
... A565: 2026 | B565: 1 | C565: 46034 | D565: 225208 | E565: NAK ARMSTRONG | F565: WJEW | G565: SS26 | H565: EARRINGS | I565: 1.9193625e+08 | J565: RWR | K565: 1 | L565: =InventoryTY[[#This Row],[Landed Cost]]*InventoryTY[[#This Row],[Inventory Qty]] -> 1.9193625e+08

Sheet Report date
A1: Date: 12/01/2026

Sheet Associate Status
A1: Store | B1: Associate | C1: Status
A2: RHN | B2: CHINH_NGUYEN | C2: Active
A3: RHN | B3: DIEM_NGUYEN | C3: Retired
A4: RHN | B4: DIEU_NGUYEN | C4: Retired
A5: RHN | B5: HA_NGUYEN | C5: Retired
A6: RHN | B6: HOA_TRAN | C6: Retired
A7: RHN | B7: HOAI_TRAN | C7: Retired
A8: RHN | B8: HUE_BUI | C8: Active
A9: RHN | B9: HUONG_NGUYEN | C9: Retired
A10: RHN | B10: HUYEN_DANG | C10: Active
A11: RHN | B11: KIEUDIEM_NGUYENHN | C11: Retired
A12: RHN | B12: LANHUONG_NGUYEN | C12: Retired
... A87: RWR | B87: VUONG_VO | C87: Active

Sheet Store lay bao  cao
A1: Store
A2: BLFD | B2: Không lấy BC
A3: DFT | B3: Không lấy BC
A4: DVF | B4: Không lấy BC
A5: ECOM | B5: Không lấy BC
A6: EVE | B6: Không lấy BC
A7: GIF | B7: Không lấy BC
A8: HQ | B8: Lấy BC
A9: LOA | B9: Không lấy BC
A10: RHA | B10: Lấy BC
A11: RHN | B11: Lấy BC
A12: RWD | B12: Lấy BC
A13: RWL | B13: Không lấy BC
... A17: TNM | B17: Không lấy BC
